Workbook

Sheet RencanaPengujian
A1: Nama KAP | C1: : | D1: Syarief, Wibawa & Rekan
A2: Nama AP | C2: : | D2: Budi T. Wibawa
A3: Nama Klien | C3: : | D3: PT YKL Indonesia
A4: Alamat Klien | C4: : | D4: Jalan Millenium IV Blok A 24/7, Kawasan Industri Millenium, Peusar/Panongan, Tangerang
A5: Tahun Buku | C5: : | D5: Audit Laporan Keuangan untuk Tahun yang Berakhir 31 Desember 2024
A6: Indeks KKA | C6: : | D6: RR.RPH
A7: Nama Indeks | C7: : | D7: Rencana Pengujian dan Hasilnya
A8: Periode | C8: : | D8: Current | G8: 6
B10: RENCANA PENGUJIAN DAN HASILNYA
B12: Simpulan | D12: Rencana pengujian dan hasilnya sudah memadai
D14: Jelaskan dasar kesimpulan di atas
B15: Status KKA
B16: Completed
A18: Trial Balance | G18: Current | H18: Periksa | K18: Pengujian | O18: Risk Analysis | W18: Sampling | Y18: Hasil Pengujian
A19: Header | D19: no_N | E19: no_O | F19: Nama_akun | G19: =IF($D$8="Interim",TB_audited!G2,TB_audited!E2) -> 45657 | H19: AP | I19: ToD | J19: I/YE | K19: Periksa Langsung Ya/Tdk | L19: Sampling Ya/Tdk | M19: Populasi (Rp) | N19: Sampling (Rp) | O19: M/TM | P19: ROMM | Q19: Significant Account | R19: AP Result H/M/N | S19: Performance Materiality | T19: Risk Factor Adjutment | U19: Specific Materiality | V19: Confidence Factor | W19: Sample Interval | X19: Jumlah Sample | Y19: Lebih Salah Saji | Z19: Kurang Salah Saji | AA19: Status | AB19: ToD
A20: =TB_audited!A3 -> Trade receivable | D20: =TB_audited!B3 -> 11201 | E20: =TB_audited!C3 -> 100/0000 | F20: =TB_audited!D3 -> TRADE DEBTORS - IDR | G20: =IF($D$8="Interim",TB_audited!G3,TB_audited!E3) -> 18567911215 | H20: =IFERROR(VLOOKUP($A20,RA_result!$B$3:$N$62,11,0),"") | I20: =IFERROR(VLOOKUP($A20,RA_result!$B$3:$N$62,12,0),"") -> Ya | J20: =IFERROR(VLOOKUP($A20,RA_result!$B$3:$N$62,13,0),"") -> YE | K20: Tidak | L20: Ya | M20: 9728145173 | N20: =G20-M20 -> 8839766042 | O20: =IFERROR(VLOOKUP($A20,RA_result!$B$3:$N$62,7,0),"") -> M | P20: =IFERROR(VLOOKUP($A20,RA_result!$B$3:$N$62,9,0),"") -> M | Q20: =IFERROR(VLOOKUP($A20,RA_result!$B$3:$N$62,10,0),"") | R20: N | S20: =IFERROR(VLOOKUP($A20,RA_result!$B$3:$N$62,4,0),"") -> 1.0535504e+09 | T20: 0.9 | U20: =IFERROR(IF(VLOOKUP($A20,RA_result!$B$3:$N$62,6,0)="",S20*T20,VLOOKUP($A20,RA_result!$B$3:$N$62,6,0)),"") -> 9.4819535e+08 | V20: 1.9 | W20: =IFERROR((S20*30%)/V20,0) -> 1.6635006e+08 | X20: =IFERROR(N20/W20,0) -> 53.139542 | Y20: 2.6519298e+08 | Z20: -2.6519298e+08 | AA20: =IF(OR(U20="",Y20="",Z20=""),"",IF(AND(U20>Y20,-U20<Z20),"Ok","Not Ok")) -> Ok
A21: =TB_audited!A4 -> Trade receivable | D21: =TB_audited!B4 -> 11202 | E21: =TB_audited!C4 -> 100/0001 | F21: =TB_audited!D4 -> Provision of Allowance Bad Debts | G21: =IF($D$8="Interim",TB_audited!G4,TB_audited!E4) -> -2286452814 | H21: =IFERROR(VLOOKUP($A21,RA_result!$B$3:$N$62,11,0),"") | I21: =IFERROR(VLOOKUP($A21,RA_result!$B$3:$N$62,12,0),"") -> Ya | J21: =IFERROR(VLOOKUP($A21,RA_result!$B$3:$N$62,13,0),"") -> YE | K21: Ya | L21: Tidak | M21: -2286452814 | N21: =G21-M21 -> 0 | O21: =IFERROR(VLOOKUP($A21,RA_result!$B$3:$N$62,7,0),"") -> M | P21: =IFERROR(VLOOKUP($A21,RA_result!$B$3:$N$62,9,0),"") -> M | Q21: =IFERROR(VLOOKUP($A21,RA_result!$B$3:$N$62,10,0),"") | R21: N | S21: =IFERROR(VLOOKUP($A21,RA_result!$B$3:$N$62,4,0),"") -> 1.0535504e+09 | T21: 0.65 | U21: =IFERROR(IF(VLOOKUP($A21,RA_result!$B$3:$N$62,6,0)="",S21*T21,VLOOKUP($A21,RA_result!$B$3:$N$62,6,0)),"") -> 6.8480776e+08 | V21: 1.3 | W21: =IFERROR((S21*30%)/V21,0) -> 2.4312701e+08 | X21: =IFERROR(N21/W21,0) -> 0 | AA21: =IF(OR(U21="",Y21="",Z21=""),"",IF(AND(U21>Y21,-U21<Z21),"Ok","Not Ok"))
A22: =TB_audited!A5 -> Other current asset | D22: =TB_audited!B5 -> 11901 | E22: =TB_audited!C5 -> 105/0010 | F22: =TB_audited!D5 -> YKL ENGINEERING SDN. BHD. (PJS) | G22: =IF($D$8="Interim",TB_audited!G5,TB_audited!E5) -> 0 | H22: =IFERROR(VLOOKUP($A22,RA_result!$B$3:$N$62,11,0),"") | I22: =IFERROR(VLOOKUP($A22,RA_result!$B$3:$N$62,12,0),"") | J22: =IFERROR(VLOOKUP($A22,RA_result!$B$3:$N$62,13,0),"") | M22: 0 | N22: =G22-M22 -> 0 | O22: =IFERROR(VLOOKUP($A22,RA_result!$B$3:$N$62,7,0),"") -> TM | P22: =IFERROR(VLOOKUP($A22,RA_result!$B$3:$N$62,9,0),"") -> L | Q22: =IFERROR(VLOOKUP($A22,RA_result!$B$3:$N$62,10,0),"") | R22: N | S22: =IFERROR(VLOOKUP($A22,RA_result!$B$3:$N$62,4,0),"") -> 1.0535504e+09 | T22: 0.9 | U22: =IFERROR(IF(VLOOKUP($A22,RA_result!$B$3:$N$62,6,0)="",S22*T22,VLOOKUP($A22,RA_result!$B$3:$N$62,6,0)),"") -> 9.4819535e+08 | W22: =IFERROR((S22*30%)/V22,0) -> 0 | X22: =IFERROR(N22/W22,0) -> 0 | AA22: =IF(OR(U22="",Y22="",Z22=""),"",IF(AND(U22>Y22,-U22<Z22),"Ok","Not Ok"))
A23: =TB_audited!A6 -> Other current asset | D23: =TB_audited!B6 -> 11902 | E23: =TB_audited!C6 -> 105/0060 | F23: =TB_audited!D6 -> PT. KMT ENGINEERING NUSANTARA (PJS) | G23: =IF($D$8="Interim",TB_audited!G6,TB_audited!E6) -> 0 | H23: =IFERROR(VLOOKUP($A23,RA_result!$B$3:$N$62,11,0),"") | I23: =IFERROR(VLOOKUP($A23,RA_result!$B$3:$N$62,12,0),"") | J23: =IFERROR(VLOOKUP($A23,RA_result!$B$3:$N$62,13,0),"") | M23: 0 | N23: =G23-M23 -> 0 | O23: =IFERROR(VLOOKUP($A23,RA_result!$B$3:$N$62,7,0),"") -> TM | P23: =IFERROR(VLOOKUP($A23,RA_result!$B$3:$N$62,9,0),"") -> L | Q23: =IFERROR(VLOOKUP($A23,RA_result!$B$3:$N$62,10,0),"") | R23: N | S23: =IFERROR(VLOOKUP($A23,RA_result!$B$3:$N$62,4,0),"") -> 1.0535504e+09 | T23: 0.9 | U23: =IFERROR(IF(VLOOKUP($A23,RA_result!$B$3:$N$62,6,0)="",S23*T23,VLOOKUP($A23,RA_result!$B$3:$N$62,6,0)),"") -> 9.4819535e+08 | W23: =IFERROR((S23*30%)/V23,0) -> 0 | X23: =IFERROR(N23/W23,0) -> 0 | AA23: =IF(OR(U23="",Y23="",Z23=""),"",IF(AND(U23>Y23,-U23<Z23),"Ok","Not Ok"))
A24: =TB_audited!A7 -> Cash and cash equivalent | D24: =TB_audited!B7 -> 11101 | E24: =TB_audited!C7 -> 110/0000 | F24: =TB_audited!D7 -> CASH IN HAND | G24: =IF($D$8="Interim",TB_audited!G7,TB_audited!E7) -> 23836004 | H24: =IFERROR(VLOOKUP($A24,RA_result!$B$3:$N$62,11,0),"") | I24: =IFERROR(VLOOKUP($A24,RA_result!$B$3:$N$62,12,0),"") -> Ya | J24: =IFERROR(VLOOKUP($A24,RA_result!$B$3:$N$62,13,0),"") -> YE | K24: Ya | L24: Tidak | M24: 23836004 | N24: =G24-M24 -> 0 | O24: =IFERROR(VLOOKUP($A24,RA_result!$B$3:$N$62,7,0),"") -> M | P24: =IFERROR(VLOOKUP($A24,RA_result!$B$3:$N$62,9,0),"") -> L | Q24: =IFERROR(VLOOKUP($A24,RA_result!$B$3:$N$62,10,0),"") | R24: N | S24: =IFERROR(VLOOKUP($A24,RA_result!$B$3:$N$62,4,0),"") -> 1.0535504e+09 | T24: 0.9 | U24: =IFERROR(IF(VLOOKUP($A24,RA_result!$B$3:$N$62,6,0)="",S24*T24,VLOOKUP($A24,RA_result!$B$3:$N$62,6,0)),"") -> 9.4819535e+08 | V24: 1.3 | W24: =IFERROR((S24*30%)/V24,0) -> 2.4312701e+08 | X24: =IFERROR(N24/W24,0) -> 0 | AA24: =IF(OR(U24="",Y24="",Z24=""),"",IF(AND(U24>Y24,-U24<Z24),"Ok","Not Ok"))
A25: =TB_audited!A8 -> Cash and cash equivalent | D25: =TB_audited!B8 -> 11102 | E25: =TB_audited!C8 -> 120/0030 | F25: =TB_audited!D8 -> CASH AT BANK-BCA (2ND) A/C : 764BCA (2ND) A/C : 7640669998 IDR | G25: =IF($D$8="Interim",TB_audited!G8,TB_audited!E8) -> 21825626 | H25: =IFERROR(VLOOKUP($A25,RA_result!$B$3:$N$62,11,0),"") | I25: =IFERROR(VLOOKUP($A25,RA_result!$B$3:$N$62,12,0),"") -> Ya | J25: =IFERROR(VLOOKUP($A25,RA_result!$B$3:$N$62,13,0),"") -> YE | K25: Ya | L25: Tidak | M25: 21825626 | N25: =G25-M25 -> 0 | O25: =IFERROR(VLOOKUP($A25,RA_result!$B$3:$N$62,7,0),"") -> M | P25: =IFERROR(VLOOKUP($A25,RA_result!$B$3:$N$62,9,0),"") -> L | Q25: =IFERROR(VLOOKUP($A25,RA_result!$B$3:$N$62,10,0),"") | R25: N | S25: =IFERROR(VLOOKUP($A25,RA_result!$B$3:$N$62,4,0),"") -> 1.0535504e+09 | T25: 0.9 | U25: =IFERROR(IF(VLOOKUP($A25,RA_result!$B$3:$N$62,6,0)="",S25*T25,VLOOKUP($A25,RA_result!$B$3:$N$62,6,0)),"") -> 9.4819535e+08 | V25: 1.3 | W25: =IFERROR((S25*30%)/V25,0) -> 2.4312701e+08 | X25: =IFERROR(N25/W25,0) -> 0 | AA25: =IF(OR(U25="",Y25="",Z25=""),"",IF(AND(U25>Y25,-U25<Z25),"Ok","Not Ok"))
A26: =TB_audited!A9 -> Cash and cash equivalent | D26: =TB_audited!B9 -> 11103 | E26: =TB_audited!C9 -> 120/0040 | F26: =TB_audited!D9 -> CASH AT BANK-BCA (EMG) A/C : 764BCA (EMG) A/C : 7640669599 IDR | G26: =IF($D$8="Interim",TB_audited!G9,TB_audited!E9) -> 2.487905e+08 | H26: =IFERROR(VLOOKUP($A26,RA_result!$B$3:$N$62,11,0),"") | I26: =IFERROR(VLOOKUP($A26,RA_result!$B$3:$N$62,12,0),"") -> Ya | J26: =IFERROR(VLOOKUP($A26,RA_result!$B$3:$N$62,13,0),"") -> YE | K26: Ya | L26: Tidak | M26: 2.487905e+08 | N26: =G26-M26 -> 0 | O26: =IFERROR(VLOOKUP($A26,RA_result!$B$3:$N$62,7,0),"") -> M | P26: =IFERROR(VLOOKUP($A26,RA_result!$B$3:$N$62,9,0),"") -> L | Q26: =IFERROR(VLOOKUP($A26,RA_result!$B$3:$N$62,10,0),"") | R26: N | S26: =IFERROR(VLOOKUP($A26,RA_result!$B$3:$N$62,4,0),"") -> 1.0535504e+09 | T26: 0.9 | U26: =IFERROR(IF(VLOOKUP($A26,RA_result!$B$3:$N$62,6,0)="",S26*T26,VLOOKUP($A26,RA_result!$B$3:$N$62,6,0)),"") -> 9.4819535e+08 | V26: 1.3 | W26: =IFERROR((S26*30%)/V26,0) -> 2.4312701e+08 | X26: =IFERROR(N26/W26,0) -> 0 | AA26: =IF(OR(U26="",Y26="",Z26=""),"",IF(AND(U26>Y26,-U26<Z26),"Ok","Not Ok"))
A27: =TB_audited!A10 -> Cash and cash equivalent | D27: =TB_audited!B10 -> 11104 | E27: =TB_audited!C10 -> 120/0050 | F27: =TB_audited!D10 -> CASH AT BANK-MANDIRI A/C : 118003MANDIRI A/C : 1180033355677 IDR | G27: =IF($D$8="Interim",TB_audited!G10,TB_audited!E10) -> 3.3120579e+10 | H27: =IFERROR(VLOOKUP($A27,RA_result!$B$3:$N$62,11,0),"") | I27: =IFERROR(VLOOKUP($A27,RA_result!$B$3:$N$62,12,0),"") -> Ya | J27: =IFERROR(VLOOKUP($A27,RA_result!$B$3:$N$62,13,0),"") -> YE | K27: Ya | L27: Tidak | M27: 3.3120579e+10 | N27: =G27-M27 -> 0 | O27: =IFERROR(VLOOKUP($A27,RA_result!$B$3:$N$62,7,0),"") -> M | P27: =IFERROR(VLOOKUP($A27,RA_result!$B$3:$N$62,9,0),"") -> L | Q27: =IFERROR(VLOOKUP($A27,RA_result!$B$3:$N$62,10,0),"") | R27: N | S27: =IFERROR(VLOOKUP($A27,RA_result!$B$3:$N$62,4,0),"") -> 1.0535504e+09 | T27: 0.9 | U27: =IFERROR(IF(VLOOKUP($A27,RA_result!$B$3:$N$62,6,0)="",S27*T27,VLOOKUP($A27,RA_result!$B$3:$N$62,6,0)),"") -> 9.4819535e+08 | V27: 1.3 | W27: =IFERROR((S27*30%)/V27,0) -> 2.4312701e+08 | X27: =IFERROR(N27/W27,0) -> 0 | AA27: =IF(OR(U27="",Y27="",Z27=""),"",IF(AND(U27>Y27,-U27<Z27),"Ok","Not Ok"))
A28: =TB_audited!A11 -> Cash and cash equivalent | D28: =TB_audited!B11 -> 11105 | E28: =TB_audited!C11 -> 120/0100 | F28: =TB_audited!D11 -> CASH AT BANK-MANDIRI A/C : 1180007MANDIRI A/C : 1180007832388 USD2 | G28: =IF($D$8="Interim",TB_audited!G11,TB_audited!E11) -> 0 | H28: =IFERROR(VLOOKUP($A28,RA_result!$B$3:$N$62,11,0),"") | I28: =IFERROR(VLOOKUP($A28,RA_result!$B$3:$N$62,12,0),"") -> Ya | J28: =IFERROR(VLOOKUP($A28,RA_result!$B$3:$N$62,13,0),"") -> YE | K28: Ya | L28: Tidak | M28: 0 | N28: =G28-M28 -> 0 | O28: =IFERROR(VLOOKUP($A28,RA_result!$B$3:$N$62,7,0),"") -> M | P28: =IFERROR(VLOOKUP($A28,RA_result!$B$3:$N$62,9,0),"") -> L | Q28: =IFERROR(VLOOKUP($A28,RA_result!$B$3:$N$62,10,0),"") | R28: N | S28: =IFERROR(VLOOKUP($A28,RA_result!$B$3:$N$62,4,0),"") -> 1.0535504e+09 | T28: 0.9 | U28: =IFERROR(IF(VLOOKUP($A28,RA_result!$B$3:$N$62,6,0)="",S28*T28,VLOOKUP($A28,RA_result!$B$3:$N$62,6,0)),"") -> 9.4819535e+08 | V28: 1.3 | W28: =IFERROR((S28*30%)/V28,0) -> 2.4312701e+08 | X28: =IFERROR(N28/W28,0) -> 0 | AA28: =IF(OR(U28="",Y28="",Z28=""),"",IF(AND(U28>Y28,-U28<Z28),"Ok","Not Ok"))
A29: =TB_audited!A12 -> Cash and cash equivalent | D29: =TB_audited!B12 -> 11106 | E29: =TB_audited!C12 -> 120/0140 | F29: =TB_audited!D12 -> CASH AT BANK-BNI A/C:855771775 | G29: =IF($D$8="Interim",TB_audited!G12,TB_audited!E12) -> 905130602 | H29: =IFERROR(VLOOKUP($A29,RA_result!$B$3:$N$62,11,0),"") | I29: =IFERROR(VLOOKUP($A29,RA_result!$B$3:$N$62,12,0),"") -> Ya | J29: =IFERROR(VLOOKUP($A29,RA_result!$B$3:$N$62,13,0),"") -> YE | K29: Ya | L29: Tidak | M29: 905130602 | N29: =G29-M29 -> 0 | O29: =IFERROR(VLOOKUP($A29,RA_result!$B$3:$N$62,7,0),"") -> M | P29: =IFERROR(VLOOKUP($A29,RA_result!$B$3:$N$62,9,0),"") -> L | Q29: =IFERROR(VLOOKUP($A29,RA_result!$B$3:$N$62,10,0),"") | R29: N | S29: =IFERROR(VLOOKUP($A29,RA_result!$B$3:$N$62,4,0),"") -> 1.0535504e+09 | T29: 0.9 | U29: =IFERROR(IF(VLOOKUP($A29,RA_result!$B$3:$N$62,6,0)="",S29*T29,VLOOKUP($A29,RA_result!$B$3:$N$62,6,0)),"") -> 9.4819535e+08 | V29: 1.3 | W29: =IFERROR((S29*30%)/V29,0) -> 2.4312701e+08 | X29: =IFERROR(N29/W29,0) -> 0 | AA29: =IF(OR(U29="",Y29="",Z29=""),"",IF(AND(U29>Y29,-U29<Z29),"Ok","Not Ok"))
A30: =TB_audited!A13 -> Inventory | D30: =TB_audited!B13 -> 11601 | E30: =TB_audited!C13 -> 126/1000 | F30: =TB_audited!D13 -> INVENTORY-MACHINE | G30: =IF($D$8="Interim",TB_audited!G13,TB_audited!E13) -> 333000000 | H30: =IFERROR(VLOOKUP($A30,RA_result!$B$3:$N$62,11,0),"") | I30: =IFERROR(VLOOKUP($A30,RA_result!$B$3:$N$62,12,0),"") -> Ya | J30: =IFERROR(VLOOKUP($A30,RA_result!$B$3:$N$62,13,0),"") -> YE | K30: Tidak | L30: Ya | M30: 333000000 | N30: =G30-M30 -> 0 | O30: =IFERROR(VLOOKUP($A30,RA_result!$B$3:$N$62,7,0),"") -> M | P30: =IFERROR(VLOOKUP($A30,RA_result!$B$3:$N$62,9,0),"") -> L | Q30: =IFERROR(VLOOKUP($A30,RA_result!$B$3:$N$62,10,0),"") | R30: N | S30: =IFERROR(VLOOKUP($A30,RA_result!$B$3:$N$62,4,0),"") -> 1.0535504e+09 | T30: 0.9 | U30: =IFERROR(IF(VLOOKUP($A30,RA_result!$B$3:$N$62,6,0)="",S30*T30,VLOOKUP($A30,RA_result!$B$3:$N$62,6,0)),"") -> 9.4819535e+08 | V30: 1.3 | W30: =IFERROR((S30*30%)/V30,0) -> 2.4312701e+08 | X30: =IFERROR(N30/W30,0) -> 0 | AA30: =IF(OR(U30="",Y30="",Z30=""),"",IF(AND(U30>Y30,-U30<Z30),"Ok","Not Ok"))
A31: =TB_audited!A14 -> Inventory | D31: =TB_audited!B14 -> 11602 | E31: =TB_audited!C14 -> 126/2000 | F31: =TB_audited!D14 -> INVENTORY-SPAREPARTS | G31: =IF($D$8="Interim",TB_audited!G14,TB_audited!E14) -> 1.3896503e+10 | H31: =IFERROR(VLOOKUP($A31,RA_result!$B$3:$N$62,11,0),"") | I31: =IFERROR(VLOOKUP($A31,RA_result!$B$3:$N$62,12,0),"") -> Ya | J31: =IFERROR(VLOOKUP($A31,RA_result!$B$3:$N$62,13,0),"") -> YE | K31: Ya | L31: Tidak | M31: 1.3896503e+10 | N31: =G31-M31 -> 0 | O31: =IFERROR(VLOOKUP($A31,RA_result!$B$3:$N$62,7,0),"") -> M | P31: =IFERROR(VLOOKUP($A31,RA_result!$B$3:$N$62,9,0),"") -> L | Q31: =IFERROR(VLOOKUP($A31,RA_result!$B$3:$N$62,10,0),"") | R31: N | S31: =IFERROR(VLOOKUP($A31,RA_result!$B$3:$N$62,4,0),"") -> 1.0535504e+09 | T31: 0.9 | U31: =IFERROR(IF(VLOOKUP($A31,RA_result!$B$3:$N$62,6,0)="",S31*T31,VLOOKUP($A31,RA_result!$B$3:$N$62,6,0)),"") -> 9.4819535e+08 | V31: 1.3 | W31: =IFERROR((S31*30%)/V31,0) -> 2.4312701e+08 | X31: =IFERROR(N31/W31,0) -> 0 | AA31: =IF(OR(U31="",Y31="",Z31=""),"",IF(AND(U31>Y31,-U31<Z31),"Ok","Not Ok"))
A32: =TB_audited!A15 -> Other current asset | D32: =TB_audited!B15 -> 11903 | E32: =TB_audited!C15 -> 130/0060 | F32: =TB_audited!D15 -> ADE IRAWAN | G32: =IF($D$8="Interim",TB_audited!G15,TB_audited!E15) -> 1500000 | H32: =IFERROR(VLOOKUP($A32,RA_result!$B$3:$N$62,11,0),"") | I32: =IFERROR(VLOOKUP($A32,RA_result!$B$3:$N$62,12,0),"") | J32: =IFERROR(VLOOKUP($A32,RA_result!$B$3:$N$62,13,0),"") | M32: 1500000 | N32: =G32-M32 -> 0 | O32: =IFERROR(VLOOKUP($A32,RA_result!$B$3:$N$62,7,0),"") -> TM | P32: =IFERROR(VLOOKUP($A32,RA_result!$B$3:$N$62,9,0),"") -> L | Q32: =IFERROR(VLOOKUP($A32,RA_result!$B$3:$N$62,10,0),"") | R32: N | S32: =IFERROR(VLOOKUP($A32,RA_result!$B$3:$N$62,4,0),"") -> 1.0535504e+09 | T32: 0.9 | U32: =IFERROR(IF(VLOOKUP($A32,RA_result!$B$3:$N$62,6,0)="",S32*T32,VLOOKUP($A32,RA_result!$B$3:$N$62,6,0)),"") -> 9.4819535e+08 | W32: =IFERROR((S32*30%)/V32,0) -> 0 | X32: =IFERROR(N32/W32,0) -> 0 | AA32: =IF(OR(U32="",Y32="",Z32=""),"",IF(AND(U32>Y32,-U32<Z32),"Ok","Not Ok"))
A33: =TB_audited!A16 -> Other current asset | D33: =TB_audited!B16 -> 11904 | E33: =TB_audited!C16 -> 130/0090 | F33: =TB_audited!D16 -> NURDIN ANDRIANSYAH | G33: =IF($D$8="Interim",TB_audited!G16,TB_audited!E16) -> 0 | H33: =IFERROR(VLOOKUP($A33,RA_result!$B$3:$N$62,11,0),"") | I33: =IFERROR(VLOOKUP($A33,RA_result!$B$3:$N$62,12,0),"") | J33: =IFERROR(VLOOKUP($A33,RA_result!$B$3:$N$62,13,0),"") | M33: 0 | N33: =G33-M33 -> 0 | O33: =IFERROR(VLOOKUP($A33,RA_result!$B$3:$N$62,7,0),"") -> TM | P33: =IFERROR(VLOOKUP($A33,RA_result!$B$3:$N$62,9,0),"") -> L | Q33: =IFERROR(VLOOKUP($A33,RA_result!$B$3:$N$62,10,0),"") | R33: N | S33: =IFERROR(VLOOKUP($A33,RA_result!$B$3:$N$62,4,0),"") -> 1.0535504e+09 | T33: 0.9 | U33: =IFERROR(IF(VLOOKUP($A33,RA_result!$B$3:$N$62,6,0)="",S33*T33,VLOOKUP($A33,RA_result!$B$3:$N$62,6,0)),"") -> 9.4819535e+08 | W33: =IFERROR((S33*30%)/V33,0) -> 0 | X33: =IFERROR(N33/W33,0) -> 0 | AA33: =IF(OR(U33="",Y33="",Z33=""),"",IF(AND(U33>Y33,-U33<Z33),"Ok","Not Ok"))
A34: =TB_audited!A17 -> Other current asset | D34: =TB_audited!B17 -> 11905 | E34: =TB_audited!C17 -> 130/0120 | F34: =TB_audited!D17 -> HUSNI APENDI | G34: =IF($D$8="Interim",TB_audited!G17,TB_audited!E17) -> 0 | H34: =IFERROR(VLOOKUP($A34,RA_result!$B$3:$N$62,11,0),"") | I34: =IFERROR(VLOOKUP($A34,RA_result!$B$3:$N$62,12,0),"") | J34: =IFERROR(VLOOKUP($A34,RA_result!$B$3:$N$62,13,0),"") | M34: 0 | N34: =G34-M34 -> 0 | O34: =IFERROR(VLOOKUP($A34,RA_result!$B$3:$N$62,7,0),"") -> TM | P34: =IFERROR(VLOOKUP($A34,RA_result!$B$3:$N$62,9,0),"") -> L | Q34: =IFERROR(VLOOKUP($A34,RA_result!$B$3:$N$62,10,0),"") | R34: N | S34: =IFERROR(VLOOKUP($A34,RA_result!$B$3:$N$62,4,0),"") -> 1.0535504e+09 | T34: 0.9 | U34: =IFERROR(IF(VLOOKUP($A34,RA_result!$B$3:$N$62,6,0)="",S34*T34,VLOOKUP($A34,RA_result!$B$3:$N$62,6,0)),"") -> 9.4819535e+08 | W34: =IFERROR((S34*30%)/V34,0) -> 0 | X34: =IFERROR(N34/W34,0) -> 0 | AA34: =IF(OR(U34="",Y34="",Z34=""),"",IF(AND(U34>Y34,-U34<Z34),"Ok","Not Ok"))
A35: =TB_audited!A18 -> Other current asset | D35: =TB_audited!B18 -> 11906 | E35: =TB_audited!C18 -> 130/0180 | F35: =TB_audited!D18 -> OKTA SANDRIAWAN | G35: =IF($D$8="Interim",TB_audited!G18,TB_audited!E18) -> 0 | H35: =IFERROR(VLOOKUP($A35,RA_result!$B$3:$N$62,11,0),"") | I35: =IFERROR(VLOOKUP($A35,RA_result!$B$3:$N$62,12,0),"") | J35: =IFERROR(VLOOKUP($A35,RA_result!$B$3:$N$62,13,0),"") | M35: 0 | N35: =G35-M35 -> 0 | O35: =IFERROR(VLOOKUP($A35,RA_result!$B$3:$N$62,7,0),"") -> TM | P35: =IFERROR(VLOOKUP($A35,RA_result!$B$3:$N$62,9,0),"") -> L | Q35: =IFERROR(VLOOKUP($A35,RA_result!$B$3:$N$62,10,0),"") | R35: N | S35: =IFERROR(VLOOKUP($A35,RA_result!$B$3:$N$62,4,0),"") -> 1.0535504e+09 | T35: 0.9 | U35: =IFERROR(IF(VLOOKUP($A35,RA_result!$B$3:$N$62,6,0)="",S35*T35,VLOOKUP($A35,RA_result!$B$3:$N$62,6,0)),"") -> 9.4819535e+08 | W35: =IFERROR((S35*30%)/V35,0) -> 0 | X35: =IFERROR(N35/W35,0) -> 0 | AA35: =IF(OR(U35="",Y35="",Z35=""),"",IF(AND(U35>Y35,-U35<Z35),"Ok","Not Ok"))
A36: =TB_audited!A19 -> Other current asset | D36: =TB_audited!B19 -> 11907 | E36: =TB_audited!C19 -> 130/0200 | F36: =TB_audited!D19 -> IRWAN YUWONO | G36: =IF($D$8="Interim",TB_audited!G19,TB_audited!E19) -> 2400000 | H36: =IFERROR(VLOOKUP($A36,RA_result!$B$3:$N$62,11,0),"") | I36: =IFERROR(VLOOKUP($A36,RA_result!$B$3:$N$62,12,0),"") | J36: =IFERROR(VLOOKUP($A36,RA_result!$B$3:$N$62,13,0),"") | M36: 2400000 | N36: =G36-M36 -> 0 | O36: =IFERROR(VLOOKUP($A36,RA_result!$B$3:$N$62,7,0),"") -> TM | P36: =IFERROR(VLOOKUP($A36,RA_result!$B$3:$N$62,9,0),"") -> L | Q36: =IFERROR(VLOOKUP($A36,RA_result!$B$3:$N$62,10,0),"") | R36: N | S36: =IFERROR(VLOOKUP($A36,RA_result!$B$3:$N$62,4,0),"") -> 1.0535504e+09 | T36: 0.9 | U36: =IFERROR(IF(VLOOKUP($A36,RA_result!$B$3:$N$62,6,0)="",S36*T36,VLOOKUP($A36,RA_result!$B$3:$N$62,6,0)),"") -> 9.4819535e+08 | W36: =IFERROR((S36*30%)/V36,0) -> 0 | X36: =IFERROR(N36/W36,0) -> 0 | AA36: =IF(OR(U36="",Y36="",Z36=""),"",IF(AND(U36>Y36,-U36<Z36),"Ok","Not Ok"))
A37: =TB_audited!A20 -> Other current asset | D37: =TB_audited!B20 -> 11908 | E37: =TB_audited!C20 -> 130/0210 | F37: =TB_audited!D20 -> BAHRUDIN | G37: =IF($D$8="Interim",TB_audited!G20,TB_audited!E20) -> 0 | H37: =IFERROR(VLOOKUP($A37,RA_result!$B$3:$N$62,11,0),"") | I37: =IFERROR(VLOOKUP($A37,RA_result!$B$3:$N$62,12,0),"") | J37: =IFERROR(VLOOKUP($A37,RA_result!$B$3:$N$62,13,0),"") | M37: 0 | N37: =G37-M37 -> 0 | O37: =IFERROR(VLOOKUP($A37,RA_result!$B$3:$N$62,7,0),"") -> TM | P37: =IFERROR(VLOOKUP($A37,RA_result!$B$3:$N$62,9,0),"") -> L | Q37: =IFERROR(VLOOKUP($A37,RA_result!$B$3:$N$62,10,0),"") | R37: N | S37: =IFERROR(VLOOKUP($A37,RA_result!$B$3:$N$62,4,0),"") -> 1.0535504e+09 | T37: 0.9 | U37: =IFERROR(IF(VLOOKUP($A37,RA_result!$B$3:$N$62,6,0)="",S37*T37,VLOOKUP($A37,RA_result!$B$3:$N$62,6,0)),"") -> 9.4819535e+08 | W37: =IFERROR((S37*30%)/V37,0) -> 0 | X37: =IFERROR(N37/W37,0) -> 0 | AA37: =IF(OR(U37="",Y37="",Z37=""),"",IF(AND(U37>Y37,-U37<Z37),"Ok","Not Ok"))
A38: =TB_audited!A21 -> Other current asset | D38: =TB_audited!B21 -> 11909 | E38: =TB_audited!C21 -> 130/0220 | F38: =TB_audited!D21 -> DEDI RIYADI | G38: =IF($D$8="Interim",TB_audited!G21,TB_audited!E21) -> 0 | H38: =IFERROR(VLOOKUP($A38,RA_result!$B$3:$N$62,11,0),"") | I38: =IFERROR(VLOOKUP($A38,RA_result!$B$3:$N$62,12,0),"") | J38: =IFERROR(VLOOKUP($A38,RA_result!$B$3:$N$62,13,0),"") | M38: 0 | N38: =G38-M38 -> 0 | O38: =IFERROR(VLOOKUP($A38,RA_result!$B$3:$N$62,7,0),"") -> TM | P38: =IFERROR(VLOOKUP($A38,RA_result!$B$3:$N$62,9,0),"") -> L | Q38: =IFERROR(VLOOKUP($A38,RA_result!$B$3:$N$62,10,0),"") | R38: N | S38: =IFERROR(VLOOKUP($A38,RA_result!$B$3:$N$62,4,0),"") -> 1.0535504e+09 | T38: 0.9 | U38: =IFERROR(IF(VLOOKUP($A38,RA_result!$B$3:$N$62,6,0)="",S38*T38,VLOOKUP($A38,RA_result!$B$3:$N$62,6,0)),"") -> 9.4819535e+08 | W38: =IFERROR((S38*30%)/V38,0) -> 0 | X38: =IFERROR(N38/W38,0) -> 0 | AA38: =IF(OR(U38="",Y38="",Z38=""),"",IF(AND(U38>Y38,-U38<Z38),"Ok","Not Ok"))
A39: =TB_audited!A22 -> Other current asset | D39: =TB_audited!B22 -> 11910 | E39: =TB_audited!C22 -> 130/0230 | F39: =TB_audited!D22 -> HARVY WAHYU PERDANA | G39: =IF($D$8="Interim",TB_audited!G22,TB_audited!E22) -> 0 | H39: =IFERROR(VLOOKUP($A39,RA_result!$B$3:$N$62,11,0),"") | I39: =IFERROR(VLOOKUP($A39,RA_result!$B$3:$N$62,12,0),"") | J39: =IFERROR(VLOOKUP($A39,RA_result!$B$3:$N$62,13,0),"") | M39: 0 | N39: =G39-M39 -> 0 | O39: =IFERROR(VLOOKUP($A39,RA_result!$B$3:$N$62,7,0),"") -> TM | P39: =IFERROR(VLOOKUP($A39,RA_result!$B$3:$N$62,9,0),"") -> L | Q39: =IFERROR(VLOOKUP($A39,RA_result!$B$3:$N$62,10,0),"") | R39: N | S39: =IFERROR(VLOOKUP($A39,RA_result!$B$3:$N$62,4,0),"") -> 1.0535504e+09 | T39: 0.9 | U39: =IFERROR(IF(VLOOKUP($A39,RA_result!$B$3:$N$62,6,0)="",S39*T39,VLOOKUP($A39,RA_result!$B$3:$N$62,6,0)),"") -> 9.4819535e+08 | W39: =IFERROR((S39*30%)/V39,0) -> 0 | X39: =IFERROR(N39/W39,0) -> 0 | AA39: =IF(OR(U39="",Y39="",Z39=""),"",IF(AND(U39>Y39,-U39<Z39),"Ok","Not Ok"))
A40: =TB_audited!A23 -> Other current asset | D40: =TB_audited!B23 -> 11911 | E40: =TB_audited!C23 -> 130/0250 | F40: =TB_audited!D23 -> TOMI HARIYANTO | G40: =IF($D$8="Interim",TB_audited!G23,TB_audited!E23) -> 4500000 | H40: =IFERROR(VLOOKUP($A40,RA_result!$B$3:$N$62,11,0),"") | I40: =IFERROR(VLOOKUP($A40,RA_result!$B$3:$N$62,12,0),"") | J40: =IFERROR(VLOOKUP($A40,RA_result!$B$3:$N$62,13,0),"") | M40: 4500000 | N40: =G40-M40 -> 0 | O40: =IFERROR(VLOOKUP($A40,RA_result!$B$3:$N$62,7,0),"") -> TM | P40: =IFERROR(VLOOKUP($A40,RA_result!$B$3:$N$62,9,0),"") -> L | Q40: =IFERROR(VLOOKUP($A40,RA_result!$B$3:$N$62,10,0),"") | R40: N | S40: =IFERROR(VLOOKUP($A40,RA_result!$B$3:$N$62,4,0),"") -> 1.0535504e+09 | T40: 0.9 | U40: =IFERROR(IF(VLOOKUP($A40,RA_result!$B$3:$N$62,6,0)="",S40*T40,VLOOKUP($A40,RA_result!$B$3:$N$62,6,0)),"") -> 9.4819535e+08 | W40: =IFERROR((S40*30%)/V40,0) -> 0 | X40: =IFERROR(N40/W40,0) -> 0 | AA40: =IF(OR(U40="",Y40="",Z40=""),"",IF(AND(U40>Y40,-U40<Z40),"Ok","Not Ok"))
A41: =TB_audited!A24 -> Other current asset | D41: =TB_audited!B24 -> 11912 | E41: =TB_audited!C24 -> 130/0260 | F41: =TB_audited!D24 -> SUHARTOYO | G41: =IF($D$8="Interim",TB_audited!G24,TB_audited!E24) -> 0 | H41: =IFERROR(VLOOKUP($A41,RA_result!$B$3:$N$62,11,0),"") | I41: =IFERROR(VLOOKUP($A41,RA_result!$B$3:$N$62,12,0),"") | J41: =IFERROR(VLOOKUP($A41,RA_result!$B$3:$N$62,13,0),"") | M41: 0 | N41: =G41-M41 -> 0 | O41: =IFERROR(VLOOKUP($A41,RA_result!$B$3:$N$62,7,0),"") -> TM | P41: =IFERROR(VLOOKUP($A41,RA_result!$B$3:$N$62,9,0),"") -> L | Q41: =IFERROR(VLOOKUP($A41,RA_result!$B$3:$N$62,10,0),"") | R41: N | S41: =IFERROR(VLOOKUP($A41,RA_result!$B$3:$N$62,4,0),"") -> 1.0535504e+09 | T41: 0.9 | U41: =IFERROR(IF(VLOOKUP($A41,RA_result!$B$3:$N$62,6,0)="",S41*T41,VLOOKUP($A41,RA_result!$B$3:$N$62,6,0)),"") -> 9.4819535e+08 | W41: =IFERROR((S41*30%)/V41,0) -> 0 | X41: =IFERROR(N41/W41,0) -> 0 | AA41: =IF(OR(U41="",Y41="",Z41=""),"",IF(AND(U41>Y41,-U41<Z41),"Ok","Not Ok"))
A42: =TB_audited!A25 -> Other current asset | D42: =TB_audited!B25 -> 11913 | E42: =TB_audited!C25 -> 140/0050 | F42: =TB_audited!D25 -> IRWAN YUWONO | G42: =IF($D$8="Interim",TB_audited!G25,TB_audited!E25) -> 6600000 | H42: =IFERROR(VLOOKUP($A42,RA_result!$B$3:$N$62,11,0),"") | I42: =IFERROR(VLOOKUP($A42,RA_result!$B$3:$N$62,12,0),"") | J42: =IFERROR(VLOOKUP($A42,RA_result!$B$3:$N$62,13,0),"") | M42: 6600000 | N42: =G42-M42 -> 0 | O42: =IFERROR(VLOOKUP($A42,RA_result!$B$3:$N$62,7,0),"") -> TM | P42: =IFERROR(VLOOKUP($A42,RA_result!$B$3:$N$62,9,0),"") -> L | Q42: =IFERROR(VLOOKUP($A42,RA_result!$B$3:$N$62,10,0),"") | R42: N | S42: =IFERROR(VLOOKUP($A42,RA_result!$B$3:$N$62,4,0),"") -> 1.0535504e+09 | T42: 0.9 | U42: =IFERROR(IF(VLOOKUP($A42,RA_result!$B$3:$N$62,6,0)="",S42*T42,VLOOKUP($A42,RA_result!$B$3:$N$62,6,0)),"") -> 9.4819535e+08 | W42: =IFERROR((S42*30%)/V42,0) -> 0 | X42: =IFERROR(N42/W42,0) -> 0 | AA42: =IF(OR(U42="",Y42="",Z42=""),"",IF(AND(U42>Y42,-U42<Z42),"Ok","Not Ok"))
A43: =TB_audited!A26 -> Other current asset | D43: =TB_audited!B26 -> 11914 | E43: =TB_audited!C26 -> 140/0370 | F43: =TB_audited!D26 -> SUHARTOYO | G43: =IF($D$8="Interim",TB_audited!G26,TB_audited!E26) -> 7100000 | H43: =IFERROR(VLOOKUP($A43,RA_result!$B$3:$N$62,11,0),"") | I43: =IFERROR(VLOOKUP($A43,RA_result!$B$3:$N$62,12,0),"") | J43: =IFERROR(VLOOKUP($A43,RA_result!$B$3:$N$62,13,0),"") | M43: 7100000 | N43: =G43-M43 -> 0 | O43: =IFERROR(VLOOKUP($A43,RA_result!$B$3:$N$62,7,0),"") -> TM | P43: =IFERROR(VLOOKUP($A43,RA_result!$B$3:$N$62,9,0),"") -> L | Q43: =IFERROR(VLOOKUP($A43,RA_result!$B$3:$N$62,10,0),"") | R43: N | S43: =IFERROR(VLOOKUP($A43,RA_result!$B$3:$N$62,4,0),"") -> 1.0535504e+09 | T43: 0.9 | U43: =IFERROR(IF(VLOOKUP($A43,RA_result!$B$3:$N$62,6,0)="",S43*T43,VLOOKUP($A43,RA_result!$B$3:$N$62,6,0)),"") -> 9.4819535e+08 | W43: =IFERROR((S43*30%)/V43,0) -> 0 | X43: =IFERROR(N43/W43,0) -> 0 | AA43: =IF(OR(U43="",Y43="",Z43=""),"",IF(AND(U43>Y43,-U43<Z43),"Ok","Not Ok"))
... A45: =TB_audited!A28 -> Other current asset | D45: =TB_audited!B28 -> 11916 | E45: =TB_audited!C28 -> 140/0503 | F45: =TB_audited!D28 -> ALFI FADLI RUFI AZI | G45: =IF($D$8="Interim",TB_audited!G28,TB_audited!E28) -> 6900000 | H45: =IFERROR(VLOOKUP($A45,RA_result!$B$3:$N$62,11,0),"") | I45: =IFERROR(VLOOKUP($A45,RA_result!$B$3:$N$62,12,0),"") | J45: =IFERROR(VLOOKUP($A45,RA_result!$B$3:$N$62,13,0),"") | M45: 6900000 | N45: =G45-M45 -> 0 | O45: =IFERROR(VLOOKUP($A45,RA_result!$B$3:$N$62,7,0),"") -> TM | P45: =IFERROR(VLOOKUP($A45,RA_result!$B$3:$N$62,9,0),"") -> L | Q45: =IFERROR(VLOOKUP($A45,RA_result!$B$3:$N$62,10,0),"") | R45: N | S45: =IFERROR(VLOOKUP($A45,RA_result!$B$3:$N$62,4,0),"") -> 1.0535504e+09 | T45: 0.9 | U45: =IFERROR(IF(VLOOKUP($A45,RA_result!$B$3:$N$62,6,0)="",S45*T45,VLOOKUP($A45,RA_result!$B$3:$N$62,6,0)),"") -> 9.4819535e+08 | W45: =IFERROR((S45*30%)/V45,0) -> 0 | X45: =IFERROR(N45/W45,0) -> 0 | AA45: =IF(OR(U45="",Y45="",Z45=""),"",IF(AND(U45>Y45,-U45<Z45),"Ok","Not Ok"))
A46: =TB_audited!A29 -> Prepayment | D46: =TB_audited!B29 -> 11701 | E46: =TB_audited!C29 -> 170/0010 | F46: =TB_audited!D29 -> DEPOSITS-RENTAL OF PHOTOCOPY | G46: =IF($D$8="Interim",TB_audited!G29,TB_audited!E29) -> 250000 | H46: =IFERROR(VLOOKUP($A46,RA_result!$B$3:$N$62,11,0),"") -> Ya | I46: =IFERROR(VLOOKUP($A46,RA_result!$B$3:$N$62,12,0),"") -> Ya | J46: =IFERROR(VLOOKUP($A46,RA_result!$B$3:$N$62,13,0),"") -> YE | K46: Ya | L46: Tidak | M46: 250000 | N46: =G46-M46 -> 0 | O46: =IFERROR(VLOOKUP($A46,RA_result!$B$3:$N$62,7,0),"") -> M | P46: =IFERROR(VLOOKUP($A46,RA_result!$B$3:$N$62,9,0),"") -> M | Q46: =IFERROR(VLOOKUP($A46,RA_result!$B$3:$N$62,10,0),"") | R46: N | S46: =IFERROR(VLOOKUP($A46,RA_result!$B$3:$N$62,4,0),"") -> 1.0535504e+09 | T46: 0.65 | U46: =IFERROR(IF(VLOOKUP($A46,RA_result!$B$3:$N$62,6,0)="",S46*T46,VLOOKUP($A46,RA_result!$B$3:$N$62,6,0)),"") -> 6.8480776e+08 | V46: 1.3 | W46: =IFERROR((S46*30%)/V46,0) -> 2.4312701e+08 | X46: =IFERROR(N46/W46,0) -> 0 | AA46: =IF(OR(U46="",Y46="",Z46=""),"",IF(AND(U46>Y46,-U46<Z46),"Ok","Not Ok"))
A47: =TB_audited!A30 -> Prepayment | D47: =TB_audited!B30 -> 11702 | E47: =TB_audited!C30 -> 170/0090 | F47: =TB_audited!D30 -> PREPAYMENT-INSURANCE | G47: =IF($D$8="Interim",TB_audited!G30,TB_audited!E30) -> 7681826 | H47: =IFERROR(VLOOKUP($A47,RA_result!$B$3:$N$62,11,0),"") -> Ya | I47: =IFERROR(VLOOKUP($A47,RA_result!$B$3:$N$62,12,0),"") -> Ya | J47: =IFERROR(VLOOKUP($A47,RA_result!$B$3:$N$62,13,0),"") -> YE | K47: Ya | L47: Tidak | M47: 7681826 | N47: =G47-M47 -> 0 | O47: =IFERROR(VLOOKUP($A47,RA_result!$B$3:$N$62,7,0),"") -> M | P47: =IFERROR(VLOOKUP($A47,RA_result!$B$3:$N$62,9,0),"") -> M | Q47: =IFERROR(VLOOKUP($A47,RA_result!$B$3:$N$62,10,0),"") | R47: N | S47: =IFERROR(VLOOKUP($A47,RA_result!$B$3:$N$62,4,0),"") -> 1.0535504e+09 | T47: 0.65 | U47: =IFERROR(IF(VLOOKUP($A47,RA_result!$B$3:$N$62,6,0)="",S47*T47,VLOOKUP($A47,RA_result!$B$3:$N$62,6,0)),"") -> 6.8480776e+08 | V47: 1.3 | W47: =IFERROR((S47*30%)/V47,0) -> 2.4312701e+08 | X47: =IFERROR(N47/W47,0) -> 0 | AA47: =IF(OR(U47="",Y47="",Z47=""),"",IF(AND(U47>Y47,-U47<Z47),"Ok","Not Ok"))
A48: =TB_audited!A31 -> Prepayment | D48: =TB_audited!B31 -> 11703 | E48: =TB_audited!C31 -> 170/0200 | F48: =TB_audited!D31 -> DOWN PAYMENT PROJECT CBU | G48: =IF($D$8="Interim",TB_audited!G31,TB_audited!E31) -> 5312723044 | H48: =IFERROR(VLOOKUP($A48,RA_result!$B$3:$N$62,11,0),"") -> Ya | I48: =IFERROR(VLOOKUP($A48,RA_result!$B$3:$N$62,12,0),"") -> Ya | J48: =IFERROR(VLOOKUP($A48,RA_result!$B$3:$N$62,13,0),"") -> YE | K48: Ya | L48: Tidak | M48: 5312723044 | N48: =G48-M48 -> 0 | O48: =IFERROR(VLOOKUP($A48,RA_result!$B$3:$N$62,7,0),"") -> M | P48: =IFERROR(VLOOKUP($A48,RA_result!$B$3:$N$62,9,0),"") -> M | Q48: =IFERROR(VLOOKUP($A48,RA_result!$B$3:$N$62,10,0),"") | R48: N | S48: =IFERROR(VLOOKUP($A48,RA_result!$B$3:$N$62,4,0),"") -> 1.0535504e+09 | T48: 0.65 | U48: =IFERROR(IF(VLOOKUP($A48,RA_result!$B$3:$N$62,6,0)="",S48*T48,VLOOKUP($A48,RA_result!$B$3:$N$62,6,0)),"") -> 6.8480776e+08 | V48: 1.3 | W48: =IFERROR((S48*30%)/V48,0) -> 2.4312701e+08 | X48: =IFERROR(N48/W48,0) -> 0 | AA48: =IF(OR(U48="",Y48="",Z48=""),"",IF(AND(U48>Y48,-U48<Z48),"Ok","Not Ok"))
A49: =TB_audited!A32 -> Prepayment | D49: =TB_audited!B32 -> 11704 | E49: =TB_audited!C32 -> 170/0700 | F49: =TB_audited!D32 -> DOWN PAYMENT PROJECT GHOM/MOM | G49: =IF($D$8="Interim",TB_audited!G32,TB_audited!E32) -> 0 | H49: =IFERROR(VLOOKUP($A49,RA_result!$B$3:$N$62,11,0),"") -> Ya | I49: =IFERROR(VLOOKUP($A49,RA_result!$B$3:$N$62,12,0),"") -> Ya | J49: =IFERROR(VLOOKUP($A49,RA_result!$B$3:$N$62,13,0),"") -> YE | K49: Ya | L49: Tidak | M49: 0 | N49: =G49-M49 -> 0 | O49: =IFERROR(VLOOKUP($A49,RA_result!$B$3:$N$62,7,0),"") -> M | P49: =IFERROR(VLOOKUP($A49,RA_result!$B$3:$N$62,9,0),"") -> M | Q49: =IFERROR(VLOOKUP($A49,RA_result!$B$3:$N$62,10,0),"") | R49: N | S49: =IFERROR(VLOOKUP($A49,RA_result!$B$3:$N$62,4,0),"") -> 1.0535504e+09 | T49: 0.65 | U49: =IFERROR(IF(VLOOKUP($A49,RA_result!$B$3:$N$62,6,0)="",S49*T49,VLOOKUP($A49,RA_result!$B$3:$N$62,6,0)),"") -> 6.8480776e+08 | V49: 1.3 | W49: =IFERROR((S49*30%)/V49,0) -> 2.4312701e+08 | X49: =IFERROR(N49/W49,0) -> 0 | AA49: =IF(OR(U49="",Y49="",Z49=""),"",IF(AND(U49>Y49,-U49<Z49),"Ok","Not Ok"))
A50: =TB_audited!A33 -> Prepayment | D50: =TB_audited!B33 -> 11705 | E50: =TB_audited!C33 -> 170/0201 | F50: =TB_audited!D33 -> Provision impairmanet cash advance | G50: =IF($D$8="Interim",TB_audited!G33,TB_audited!E33) -> -3187633826 | H50: =IFERROR(VLOOKUP($A50,RA_result!$B$3:$N$62,11,0),"") -> Ya | I50: =IFERROR(VLOOKUP($A50,RA_result!$B$3:$N$62,12,0),"") -> Ya | J50: =IFERROR(VLOOKUP($A50,RA_result!$B$3:$N$62,13,0),"") -> YE | M50: -3187633826 | N50: =G50-M50 -> 0 | O50: =IFERROR(VLOOKUP($A50,RA_result!$B$3:$N$62,7,0),"") -> M | P50: =IFERROR(VLOOKUP($A50,RA_result!$B$3:$N$62,9,0),"") -> M | Q50: =IFERROR(VLOOKUP($A50,RA_result!$B$3:$N$62,10,0),"") | R50: N | S50: =IFERROR(VLOOKUP($A50,RA_result!$B$3:$N$62,4,0),"") -> 1.0535504e+09 | T50: 0.65 | U50: =IFERROR(IF(VLOOKUP($A50,RA_result!$B$3:$N$62,6,0)="",S50*T50,VLOOKUP($A50,RA_result!$B$3:$N$62,6,0)),"") -> 6.8480776e+08 | V50: 1.3 | W50: =IFERROR((S50*30%)/V50,0) -> 2.4312701e+08 | X50: =IFERROR(N50/W50,0) -> 0 | AA50: =IF(OR(U50="",Y50="",Z50=""),"",IF(AND(U50>Y50,-U50<Z50),"Ok","Not Ok"))
A51: =TB_audited!A34 -> Prepaid tax | D51: =TB_audited!B34 -> 11801 | E51: =TB_audited!C34 -> 180/0050 | F51: =TB_audited!D34 -> PPH PASAL 21 ( PCB ) | G51: =IF($D$8="Interim",TB_audited!G34,TB_audited!E34) -> 32847583 | H51: =IFERROR(VLOOKUP($A51,RA_result!$B$3:$N$62,11,0),"") | I51: =IFERROR(VLOOKUP($A51,RA_result!$B$3:$N$62,12,0),"") -> Ya | J51: =IFERROR(VLOOKUP($A51,RA_result!$B$3:$N$62,13,0),"") -> YE | K51: Ya | L51: Tidak | M51: 32847583 | N51: =G51-M51 -> 0 | O51: =IFERROR(VLOOKUP($A51,RA_result!$B$3:$N$62,7,0),"") -> M | P51: =IFERROR(VLOOKUP($A51,RA_result!$B$3:$N$62,9,0),"") -> L | Q51: =IFERROR(VLOOKUP($A51,RA_result!$B$3:$N$62,10,0),"") | R51: N | S51: =IFERROR(VLOOKUP($A51,RA_result!$B$3:$N$62,4,0),"") -> 1.0535504e+09 | T51: 0.9 | U51: =IFERROR(IF(VLOOKUP($A51,RA_result!$B$3:$N$62,6,0)="",S51*T51,VLOOKUP($A51,RA_result!$B$3:$N$62,6,0)),"") -> 2.9499411e+08 | V51: 1.3 | W51: =IFERROR((S51*30%)/V51,0) -> 2.4312701e+08 | X51: =IFERROR(N51/W51,0) -> 0 | AA51: =IF(OR(U51="",Y51="",Z51=""),"",IF(AND(U51>Y51,-U51<Z51),"Ok","Not Ok"))
A52: =TB_audited!A35 -> Prepaid tax | D52: =TB_audited!B35 -> 11802 | E52: =TB_audited!C35 -> 180/0074 | F52: =TB_audited!D35 -> PPH PASAL 28A (2024) | G52: =IF($D$8="Interim",TB_audited!G35,TB_audited!E35) -> 466204786 | H52: =IFERROR(VLOOKUP($A52,RA_result!$B$3:$N$62,11,0),"") | I52: =IFERROR(VLOOKUP($A52,RA_result!$B$3:$N$62,12,0),"") -> Ya | J52: =IFERROR(VLOOKUP($A52,RA_result!$B$3:$N$62,13,0),"") -> YE | K52: Ya | L52: Tidak | M52: 484076706 | N52: =G52-M52 -> -17871920 | O52: =IFERROR(VLOOKUP($A52,RA_result!$B$3:$N$62,7,0),"") -> M | P52: =IFERROR(VLOOKUP($A52,RA_result!$B$3:$N$62,9,0),"") -> L | Q52: =IFERROR(VLOOKUP($A52,RA_result!$B$3:$N$62,10,0),"") | R52: N | S52: =IFERROR(VLOOKUP($A52,RA_result!$B$3:$N$62,4,0),"") -> 1.0535504e+09 | T52: 0.9 | U52: =IFERROR(IF(VLOOKUP($A52,RA_result!$B$3:$N$62,6,0)="",S52*T52,VLOOKUP($A52,RA_result!$B$3:$N$62,6,0)),"") -> 2.9499411e+08 | V52: 1.3 | W52: =IFERROR((S52*30%)/V52,0) -> 2.4312701e+08 | X52: =IFERROR(N52/W52,0) -> -0.073508574 | AA52: =IF(OR(U52="",Y52="",Z52=""),"",IF(AND(U52>Y52,-U52<Z52),"Ok","Not Ok"))
A53: =TB_audited!A36 -> Fixed asset | D53: =TB_audited!B36 -> 12501 | E53: =TB_audited!C36 -> 200/0100 | F53: =TB_audited!D36 -> FREEHOLD LAND | G53: =IF($D$8="Interim",TB_audited!G36,TB_audited!E36) -> 2351082000 | H53: =IFERROR(VLOOKUP($A53,RA_result!$B$3:$N$62,11,0),"") -> Ya | I53: =IFERROR(VLOOKUP($A53,RA_result!$B$3:$N$62,12,0),"") -> Ya | J53: =IFERROR(VLOOKUP($A53,RA_result!$B$3:$N$62,13,0),"") -> YE | K53: Ya | L53: Tidak | M53: 2351082000 | N53: =G53-M53 -> 0 | O53: =IFERROR(VLOOKUP($A53,RA_result!$B$3:$N$62,7,0),"") -> M | P53: =IFERROR(VLOOKUP($A53,RA_result!$B$3:$N$62,9,0),"") -> L | Q53: =IFERROR(VLOOKUP($A53,RA_result!$B$3:$N$62,10,0),"") | R53: N | S53: =IFERROR(VLOOKUP($A53,RA_result!$B$3:$N$62,4,0),"") -> 1.0535504e+09 | T53: 0.9 | U53: =IFERROR(IF(VLOOKUP($A53,RA_result!$B$3:$N$62,6,0)="",S53*T53,VLOOKUP($A53,RA_result!$B$3:$N$62,6,0)),"") -> 9.4819535e+08 | V53: 1.3 | W53: =IFERROR((S53*30%)/V53,0) -> 2.4312701e+08 | X53: =IFERROR(N53/W53,0) -> 0 | AA53: =IF(OR(U53="",Y53="",Z53=""),"",IF(AND(U53>Y53,-U53<Z53),"Ok","Not Ok"))
A54: =TB_audited!A37 -> Fixed asset | D54: =TB_audited!B37 -> 12502 | E54: =TB_audited!C37 -> 200/0300 | F54: =TB_audited!D37 -> WAREHOUSE | G54: =IF($D$8="Interim",TB_audited!G37,TB_audited!E37) -> 9427534194 | H54: =IFERROR(VLOOKUP($A54,RA_result!$B$3:$N$62,11,0),"") -> Ya | I54: =IFERROR(VLOOKUP($A54,RA_result!$B$3:$N$62,12,0),"") -> Ya | J54: =IFERROR(VLOOKUP($A54,RA_result!$B$3:$N$62,13,0),"") -> YE | K54: Ya | L54: Tidak | M54: 9427534194 | N54: =G54-M54 -> 0 | O54: =IFERROR(VLOOKUP($A54,RA_result!$B$3:$N$62,7,0),"") -> M | P54: =IFERROR(VLOOKUP($A54,RA_result!$B$3:$N$62,9,0),"") -> L | Q54: =IFERROR(VLOOKUP($A54,RA_result!$B$3:$N$62,10,0),"") | R54: N | S54: =IFERROR(VLOOKUP($A54,RA_result!$B$3:$N$62,4,0),"") -> 1.0535504e+09 | T54: 0.9 | U54: =IFERROR(IF(VLOOKUP($A54,RA_result!$B$3:$N$62,6,0)="",S54*T54,VLOOKUP($A54,RA_result!$B$3:$N$62,6,0)),"") -> 9.4819535e+08 | V54: 1.3 | W54: =IFERROR((S54*30%)/V54,0) -> 2.4312701e+08 | X54: =IFERROR(N54/W54,0) -> 0 | AA54: =IF(OR(U54="",Y54="",Z54=""),"",IF(AND(U54>Y54,-U54<Z54),"Ok","Not Ok"))
A55: =TB_audited!A38 -> Fixed asset | D55: =TB_audited!B38 -> 12503 | E55: =TB_audited!C38 -> 200/0305 | F55: =TB_audited!D38 -> ACCUM. DEPRN. WAREHOUSE | G55: =IF($D$8="Interim",TB_audited!G38,TB_audited!E38) -> -4050622029 | H55: =IFERROR(VLOOKUP($A55,RA_result!$B$3:$N$62,11,0),"") -> Ya | I55: =IFERROR(VLOOKUP($A55,RA_result!$B$3:$N$62,12,0),"") -> Ya | J55: =IFERROR(VLOOKUP($A55,RA_result!$B$3:$N$62,13,0),"") -> YE | M55: -4050622029 | N55: =G55-M55 -> 0 | O55: =IFERROR(VLOOKUP($A55,RA_result!$B$3:$N$62,7,0),"") -> M | P55: =IFERROR(VLOOKUP($A55,RA_result!$B$3:$N$62,9,0),"") -> L | Q55: =IFERROR(VLOOKUP($A55,RA_result!$B$3:$N$62,10,0),"") | R55: N | S55: =IFERROR(VLOOKUP($A55,RA_result!$B$3:$N$62,4,0),"") -> 1.0535504e+09 | T55: 0.9 | U55: =IFERROR(IF(VLOOKUP($A55,RA_result!$B$3:$N$62,6,0)="",S55*T55,VLOOKUP($A55,RA_result!$B$3:$N$62,6,0)),"") -> 9.4819535e+08 | V55: 1.3 | W55: =IFERROR((S55*30%)/V55,0) -> 2.4312701e+08 | X55: =IFERROR(N55/W55,0) -> 0 | AA55: =IF(OR(U55="",Y55="",Z55=""),"",IF(AND(U55>Y55,-U55<Z55),"Ok","Not Ok"))
A56: =TB_audited!A39 -> Fixed asset | D56: =TB_audited!B39 -> 12504 | E56: =TB_audited!C39 -> 200/0500 | F56: =TB_audited!D39 -> OFFICE EQUIPMENT | G56: =IF($D$8="Interim",TB_audited!G39,TB_audited!E39) -> 707586797 | H56: =IFERROR(VLOOKUP($A56,RA_result!$B$3:$N$62,11,0),"") -> Ya | I56: =IFERROR(VLOOKUP($A56,RA_result!$B$3:$N$62,12,0),"") -> Ya | J56: =IFERROR(VLOOKUP($A56,RA_result!$B$3:$N$62,13,0),"") -> YE | K56: Ya | L56: Tidak | M56: 707586797 | N56: =G56-M56 -> 0 | O56: =IFERROR(VLOOKUP($A56,RA_result!$B$3:$N$62,7,0),"") -> M | P56: =IFERROR(VLOOKUP($A56,RA_result!$B$3:$N$62,9,0),"") -> L | Q56: =IFERROR(VLOOKUP($A56,RA_result!$B$3:$N$62,10,0),"") | R56: N | S56: =IFERROR(VLOOKUP($A56,RA_result!$B$3:$N$62,4,0),"") -> 1.0535504e+09 | T56: 0.9 | U56: =IFERROR(IF(VLOOKUP($A56,RA_result!$B$3:$N$62,6,0)="",S56*T56,VLOOKUP($A56,RA_result!$B$3:$N$62,6,0)),"") -> 9.4819535e+08 | V56: 1.3 | W56: =IFERROR((S56*30%)/V56,0) -> 2.4312701e+08 | X56: =IFERROR(N56/W56,0) -> 0 | AA56: =IF(OR(U56="",Y56="",Z56=""),"",IF(AND(U56>Y56,-U56<Z56),"Ok","Not Ok"))
A57: =TB_audited!A40 -> Fixed asset | D57: =TB_audited!B40 -> 12505 | E57: =TB_audited!C40 -> 200/0505 | F57: =TB_audited!D40 -> ACCUM. DEPRN. OFFICE EQUIPMENT | G57: =IF($D$8="Interim",TB_audited!G40,TB_audited!E40) -> -668924449 | H57: =IFERROR(VLOOKUP($A57,RA_result!$B$3:$N$62,11,0),"") -> Ya | I57: =IFERROR(VLOOKUP($A57,RA_result!$B$3:$N$62,12,0),"") -> Ya | J57: =IFERROR(VLOOKUP($A57,RA_result!$B$3:$N$62,13,0),"") -> YE | M57: -668924449 | N57: =G57-M57 -> 0 | O57: =IFERROR(VLOOKUP($A57,RA_result!$B$3:$N$62,7,0),"") -> M | P57: =IFERROR(VLOOKUP($A57,RA_result!$B$3:$N$62,9,0),"") -> L | Q57: =IFERROR(VLOOKUP($A57,RA_result!$B$3:$N$62,10,0),"") | R57: N | S57: =IFERROR(VLOOKUP($A57,RA_result!$B$3:$N$62,4,0),"") -> 1.0535504e+09 | T57: 0.9 | U57: =IFERROR(IF(VLOOKUP($A57,RA_result!$B$3:$N$62,6,0)="",S57*T57,VLOOKUP($A57,RA_result!$B$3:$N$62,6,0)),"") -> 9.4819535e+08 | V57: 1.3 | W57: =IFERROR((S57*30%)/V57,0) -> 2.4312701e+08 | X57: =IFERROR(N57/W57,0) -> 0 | AA57: =IF(OR(U57="",Y57="",Z57=""),"",IF(AND(U57>Y57,-U57<Z57),"Ok","Not Ok"))
A58: =TB_audited!A41 -> Fixed asset | D58: =TB_audited!B41 -> 12506 | E58: =TB_audited!C41 -> 200/0600 | F58: =TB_audited!D41 -> MOTOR VEHICLE | G58: =IF($D$8="Interim",TB_audited!G41,TB_audited!E41) -> 361959091 | H58: =IFERROR(VLOOKUP($A58,RA_result!$B$3:$N$62,11,0),"") -> Ya | I58: =IFERROR(VLOOKUP($A58,RA_result!$B$3:$N$62,12,0),"") -> Ya | J58: =IFERROR(VLOOKUP($A58,RA_result!$B$3:$N$62,13,0),"") -> YE | K58: Ya | L58: Tidak | M58: 361959091 | N58: =G58-M58 -> 0 | O58: =IFERROR(VLOOKUP($A58,RA_result!$B$3:$N$62,7,0),"") -> M | P58: =IFERROR(VLOOKUP($A58,RA_result!$B$3:$N$62,9,0),"") -> L | Q58: =IFERROR(VLOOKUP($A58,RA_result!$B$3:$N$62,10,0),"") | R58: N | S58: =IFERROR(VLOOKUP($A58,RA_result!$B$3:$N$62,4,0),"") -> 1.0535504e+09 | T58: 0.9 | U58: =IFERROR(IF(VLOOKUP($A58,RA_result!$B$3:$N$62,6,0)="",S58*T58,VLOOKUP($A58,RA_result!$B$3:$N$62,6,0)),"") -> 9.4819535e+08 | V58: 1.3 | W58: =IFERROR((S58*30%)/V58,0) -> 2.4312701e+08 | X58: =IFERROR(N58/W58,0) -> 0 | AA58: =IF(OR(U58="",Y58="",Z58=""),"",IF(AND(U58>Y58,-U58<Z58),"Ok","Not Ok"))
A59: =TB_audited!A42 -> Fixed asset | D59: =TB_audited!B42 -> 12507 | E59: =TB_audited!C42 -> 200/0605 | F59: =TB_audited!D42 -> ACCUM. DEPRN. MOTOR VEHICLE | G59: =IF($D$8="Interim",TB_audited!G42,TB_audited!E42) -> -361959091 | H59: =IFERROR(VLOOKUP($A59,RA_result!$B$3:$N$62,11,0),"") -> Ya | I59: =IFERROR(VLOOKUP($A59,RA_result!$B$3:$N$62,12,0),"") -> Ya | J59: =IFERROR(VLOOKUP($A59,RA_result!$B$3:$N$62,13,0),"") -> YE | M59: -361959091 | N59: =G59-M59 -> 0 | O59: =IFERROR(VLOOKUP($A59,RA_result!$B$3:$N$62,7,0),"") -> M | P59: =IFERROR(VLOOKUP($A59,RA_result!$B$3:$N$62,9,0),"") -> L | Q59: =IFERROR(VLOOKUP($A59,RA_result!$B$3:$N$62,10,0),"") | R59: N | S59: =IFERROR(VLOOKUP($A59,RA_result!$B$3:$N$62,4,0),"") -> 1.0535504e+09 | T59: 0.9 | U59: =IFERROR(IF(VLOOKUP($A59,RA_result!$B$3:$N$62,6,0)="",S59*T59,VLOOKUP($A59,RA_result!$B$3:$N$62,6,0)),"") -> 9.4819535e+08 | V59: 1.3 | W59: =IFERROR((S59*30%)/V59,0) -> 2.4312701e+08 | X59: =IFERROR(N59/W59,0) -> 0 | AA59: =IF(OR(U59="",Y59="",Z59=""),"",IF(AND(U59>Y59,-U59<Z59),"Ok","Not Ok"))
A60: =TB_audited!A43 -> Fixed asset | D60: =TB_audited!B43 -> 12508 | E60: =TB_audited!C43 -> 200/0700 | F60: =TB_audited!D43 -> MACHINERY AND EQUIPMENT | G60: =IF($D$8="Interim",TB_audited!G43,TB_audited!E43) -> 72082517 | H60: =IFERROR(VLOOKUP($A60,RA_result!$B$3:$N$62,11,0),"") -> Ya | I60: =IFERROR(VLOOKUP($A60,RA_result!$B$3:$N$62,12,0),"") -> Ya | J60: =IFERROR(VLOOKUP($A60,RA_result!$B$3:$N$62,13,0),"") -> YE | K60: Ya | L60: Tidak | M60: 72082517 | N60: =G60-M60 -> 0 | O60: =IFERROR(VLOOKUP($A60,RA_result!$B$3:$N$62,7,0),"") -> M | P60: =IFERROR(VLOOKUP($A60,RA_result!$B$3:$N$62,9,0),"") -> L | Q60: =IFERROR(VLOOKUP($A60,RA_result!$B$3:$N$62,10,0),"") | R60: N | S60: =IFERROR(VLOOKUP($A60,RA_result!$B$3:$N$62,4,0),"") -> 1.0535504e+09 | T60: 0.9 | U60: =IFERROR(IF(VLOOKUP($A60,RA_result!$B$3:$N$62,6,0)="",S60*T60,VLOOKUP($A60,RA_result!$B$3:$N$62,6,0)),"") -> 9.4819535e+08 | V60: 1.3 | W60: =IFERROR((S60*30%)/V60,0) -> 2.4312701e+08 | X60: =IFERROR(N60/W60,0) -> 0 | AA60: =IF(OR(U60="",Y60="",Z60=""),"",IF(AND(U60>Y60,-U60<Z60),"Ok","Not Ok"))
A61: =TB_audited!A44 -> Fixed asset | D61: =TB_audited!B44 -> 12509 | E61: =TB_audited!C44 -> 200/0705 | F61: =TB_audited!D44 -> ACCUM. DEPRN. MACHINERY AND EQUIPMENT | G61: =IF($D$8="Interim",TB_audited!G44,TB_audited!E44) -> -61811793 | H61: =IFERROR(VLOOKUP($A61,RA_result!$B$3:$N$62,11,0),"") -> Ya | I61: =IFERROR(VLOOKUP($A61,RA_result!$B$3:$N$62,12,0),"") -> Ya | J61: =IFERROR(VLOOKUP($A61,RA_result!$B$3:$N$62,13,0),"") -> YE | M61: -61811793 | N61: =G61-M61 -> 0 | O61: =IFERROR(VLOOKUP($A61,RA_result!$B$3:$N$62,7,0),"") -> M | P61: =IFERROR(VLOOKUP($A61,RA_result!$B$3:$N$62,9,0),"") -> L | Q61: =IFERROR(VLOOKUP($A61,RA_result!$B$3:$N$62,10,0),"") | R61: N | S61: =IFERROR(VLOOKUP($A61,RA_result!$B$3:$N$62,4,0),"") -> 1.0535504e+09 | T61: 0.9 | U61: =IFERROR(IF(VLOOKUP($A61,RA_result!$B$3:$N$62,6,0)="",S61*T61,VLOOKUP($A61,RA_result!$B$3:$N$62,6,0)),"") -> 9.4819535e+08 | V61: 1.3 | W61: =IFERROR((S61*30%)/V61,0) -> 2.4312701e+08 | X61: =IFERROR(N61/W61,0) -> 0 | AA61: =IF(OR(U61="",Y61="",Z61=""),"",IF(AND(U61>Y61,-U61<Z61),"Ok","Not Ok"))
A62: =TB_audited!A45 -> Intangible asset | D62: =TB_audited!B45 -> 12701 | E62: =TB_audited!C45 -> 250/0100 | F62: =TB_audited!D45 -> INTANGIBLE ASSETS | G62: =IF($D$8="Interim",TB_audited!G45,TB_audited!E45) -> 115843336 | H62: =IFERROR(VLOOKUP($A62,RA_result!$B$3:$N$62,11,0),"") | I62: =IFERROR(VLOOKUP($A62,RA_result!$B$3:$N$62,12,0),"") | J62: =IFERROR(VLOOKUP($A62,RA_result!$B$3:$N$62,13,0),"") | M62: 115843336 | N62: =G62-M62 -> 0 | O62: =IFERROR(VLOOKUP($A62,RA_result!$B$3:$N$62,7,0),"") -> TM | P62: =IFERROR(VLOOKUP($A62,RA_result!$B$3:$N$62,9,0),"") -> L | Q62: =IFERROR(VLOOKUP($A62,RA_result!$B$3:$N$62,10,0),"") | R62: N | S62: =IFERROR(VLOOKUP($A62,RA_result!$B$3:$N$62,4,0),"") -> 1.0535504e+09 | T62: 0.9 | U62: =IFERROR(IF(VLOOKUP($A62,RA_result!$B$3:$N$62,6,0)="",S62*T62,VLOOKUP($A62,RA_result!$B$3:$N$62,6,0)),"") -> 9.4819535e+08 | W62: =IFERROR((S62*30%)/V62,0) -> 0 | X62: =IFERROR(N62/W62,0) -> 0 | AA62: =IF(OR(U62="",Y62="",Z62=""),"",IF(AND(U62>Y62,-U62<Z62),"Ok","Not Ok"))
A63: =TB_audited!A46 -> Intangible asset | D63: =TB_audited!B46 -> 12702 | E63: =TB_audited!C46 -> 250/0105 | F63: =TB_audited!D46 -> ACCUM. DEPRN. INTANGIBLE ASSETS | G63: =IF($D$8="Interim",TB_audited!G46,TB_audited!E46) -> -115843336 | H63: =IFERROR(VLOOKUP($A63,RA_result!$B$3:$N$62,11,0),"") | I63: =IFERROR(VLOOKUP($A63,RA_result!$B$3:$N$62,12,0),"") | J63: =IFERROR(VLOOKUP($A63,RA_result!$B$3:$N$62,13,0),"") | M63: -115843336 | N63: =G63-M63 -> 0 | O63: =IFERROR(VLOOKUP($A63,RA_result!$B$3:$N$62,7,0),"") -> TM | P63: =IFERROR(VLOOKUP($A63,RA_result!$B$3:$N$62,9,0),"") -> L | Q63: =IFERROR(VLOOKUP($A63,RA_result!$B$3:$N$62,10,0),"") | R63: N | S63: =IFERROR(VLOOKUP($A63,RA_result!$B$3:$N$62,4,0),"") -> 1.0535504e+09 | T63: 0.9 | U63: =IFERROR(IF(VLOOKUP($A63,RA_result!$B$3:$N$62,6,0)="",S63*T63,VLOOKUP($A63,RA_result!$B$3:$N$62,6,0)),"") -> 9.4819535e+08 | W63: =IFERROR((S63*30%)/V63,0) -> 0 | X63: =IFERROR(N63/W63,0) -> 0 | AA63: =IF(OR(U63="",Y63="",Z63=""),"",IF(AND(U63>Y63,-U63<Z63),"Ok","Not Ok"))
A64: =TB_audited!A47 -> Trade payable | D64: =TB_audited!B47 -> 21101 | E64: =TB_audited!C47 -> 300/0000 | F64: =TB_audited!D47 -> TRADE CREDITORS-IDR | G64: =IF($D$8="Interim",TB_audited!G47,TB_audited!E47) -> 3612199904 | H64: =IFERROR(VLOOKUP($A64,RA_result!$B$3:$N$62,11,0),"") | I64: =IFERROR(VLOOKUP($A64,RA_result!$B$3:$N$62,12,0),"") -> Ya | J64: =IFERROR(VLOOKUP($A64,RA_result!$B$3:$N$62,13,0),"") -> YE | K64: Tidak | L64: Ya | M64: 2976706028 | N64: =G64-M64 -> 635493876 | O64: =IFERROR(VLOOKUP($A64,RA_result!$B$3:$N$62,7,0),"") -> M | P64: =IFERROR(VLOOKUP($A64,RA_result!$B$3:$N$62,9,0),"") -> L | Q64: =IFERROR(VLOOKUP($A64,RA_result!$B$3:$N$62,10,0),"") | R64: N | S64: =IFERROR(VLOOKUP($A64,RA_result!$B$3:$N$62,4,0),"") -> 1.0535504e+09 | T64: 0.8 | U64: =IFERROR(IF(VLOOKUP($A64,RA_result!$B$3:$N$62,6,0)="",S64*T64,VLOOKUP($A64,RA_result!$B$3:$N$62,6,0)),"") -> 8.4284031e+08 | V64: 1.4 | W64: =IFERROR((S64*30%)/V64,0) -> 2.257608e+08 | X64: =IFERROR(N64/W64,0) -> 2.8148991 | Y64: 69268832 | Z64: -69268832 | AA64: =IF(OR(U64="",Y64="",Z64=""),"",IF(AND(U64>Y64,-U64<Z64),"Ok","Not Ok")) -> Ok
A65: =TB_audited!A48 -> Trade payable | D65: =TB_audited!B48 -> 21102 | E65: =TB_audited!C48 -> 301/0000 | F65: =TB_audited!D48 -> TRADE CREDITORS-RM | G65: =IF($D$8="Interim",TB_audited!G48,TB_audited!E48) -> 9.0835417e+09 | H65: =IFERROR(VLOOKUP($A65,RA_result!$B$3:$N$62,11,0),"") | I65: =IFERROR(VLOOKUP($A65,RA_result!$B$3:$N$62,12,0),"") -> Ya | J65: =IFERROR(VLOOKUP($A65,RA_result!$B$3:$N$62,13,0),"") -> YE | K65: Ya | L65: Tidak | M65: 9.0835417e+09 | N65: =G65-M65 -> 0 | O65: =IFERROR(VLOOKUP($A65,RA_result!$B$3:$N$62,7,0),"") -> M | P65: =IFERROR(VLOOKUP($A65,RA_result!$B$3:$N$62,9,0),"") -> L | Q65: =IFERROR(VLOOKUP($A65,RA_result!$B$3:$N$62,10,0),"") | R65: N | S65: =IFERROR(VLOOKUP($A65,RA_result!$B$3:$N$62,4,0),"") -> 1.0535504e+09 | T65: 0.9 | U65: =IFERROR(IF(VLOOKUP($A65,RA_result!$B$3:$N$62,6,0)="",S65*T65,VLOOKUP($A65,RA_result!$B$3:$N$62,6,0)),"") -> 9.4819535e+08 | V65: 1.3 | W65: =IFERROR((S65*30%)/V65,0) -> 2.4312701e+08 | X65: =IFERROR(N65/W65,0) -> 0 | AA65: =IF(OR(U65="",Y65="",Z65=""),"",IF(AND(U65>Y65,-U65<Z65),"Ok","Not Ok"))
A66: =TB_audited!A49 -> Accruals and other payable | D66: =TB_audited!B49 -> 21201 | E66: =TB_audited!C49 -> 310/0000 | F66: =TB_audited!D49 -> ACCRUALS | G66: =IF($D$8="Interim",TB_audited!G49,TB_audited!E49) -> 14686300 | H66: =IFERROR(VLOOKUP($A66,RA_result!$B$3:$N$62,11,0),"") | I66: =IFERROR(VLOOKUP($A66,RA_result!$B$3:$N$62,12,0),"") | J66: =IFERROR(VLOOKUP($A66,RA_result!$B$3:$N$62,13,0),"") | M66: 14686300 | N66: =G66-M66 -> 0 | O66: =IFERROR(VLOOKUP($A66,RA_result!$B$3:$N$62,7,0),"") -> TM | P66: =IFERROR(VLOOKUP($A66,RA_result!$B$3:$N$62,9,0),"") -> L | Q66: =IFERROR(VLOOKUP($A66,RA_result!$B$3:$N$62,10,0),"") | R66: N | S66: =IFERROR(VLOOKUP($A66,RA_result!$B$3:$N$62,4,0),"") -> 1.0535504e+09 | T66: 0.9 | U66: =IFERROR(IF(VLOOKUP($A66,RA_result!$B$3:$N$62,6,0)="",S66*T66,VLOOKUP($A66,RA_result!$B$3:$N$62,6,0)),"") -> 9.4819535e+08 | W66: =IFERROR((S66*30%)/V66,0) -> 0 | X66: =IFERROR(N66/W66,0) -> 0 | AA66: =IF(OR(U66="",Y66="",Z66=""),"",IF(AND(U66>Y66,-U66<Z66),"Ok","Not Ok"))
A67: =TB_audited!A50 -> Accruals and other payable | D67: =TB_audited!B50 -> 21202 | E67: =TB_audited!C50 -> 311/0000 | F67: =TB_audited!D50 -> OTHER CURRENT LIABILITIES | G67: =IF($D$8="Interim",TB_audited!G50,TB_audited!E50) -> 1186894 | H67: =IFERROR(VLOOKUP($A67,RA_result!$B$3:$N$62,11,0),"") | I67: =IFERROR(VLOOKUP($A67,RA_result!$B$3:$N$62,12,0),"") | J67: =IFERROR(VLOOKUP($A67,RA_result!$B$3:$N$62,13,0),"") | M67: 1186894 | N67: =G67-M67 -> 0 | O67: =IFERROR(VLOOKUP($A67,RA_result!$B$3:$N$62,7,0),"") -> TM | P67: =IFERROR(VLOOKUP($A67,RA_result!$B$3:$N$62,9,0),"") -> L | Q67: =IFERROR(VLOOKUP($A67,RA_result!$B$3:$N$62,10,0),"") | R67: N | S67: =IFERROR(VLOOKUP($A67,RA_result!$B$3:$N$62,4,0),"") -> 1.0535504e+09 | T67: 0.9 | U67: =IFERROR(IF(VLOOKUP($A67,RA_result!$B$3:$N$62,6,0)="",S67*T67,VLOOKUP($A67,RA_result!$B$3:$N$62,6,0)),"") -> 9.4819535e+08 | W67: =IFERROR((S67*30%)/V67,0) -> 0 | X67: =IFERROR(N67/W67,0) -> 0 | AA67: =IF(OR(U67="",Y67="",Z67=""),"",IF(AND(U67>Y67,-U67<Z67),"Ok","Not Ok"))
A68: =TB_audited!A51 -> Short-term employee benefit liability | D68: =TB_audited!B51 -> 21601 | E68: =TB_audited!C51 -> 315/0000 | F68: =TB_audited!D51 -> POST EMPLOYEE BENEFIT | G68: =IF($D$8="Interim",TB_audited!G51,TB_audited!E51) -> 1247188889 | H68: =IFERROR(VLOOKUP($A68,RA_result!$B$3:$N$62,11,0),"") | I68: =IFERROR(VLOOKUP($A68,RA_result!$B$3:$N$62,12,0),"") -> Ya | J68: =IFERROR(VLOOKUP($A68,RA_result!$B$3:$N$62,13,0),"") -> YE | K68: Ya | L68: Tidak | M68: 1243215461 | N68: =G68-M68 -> 3973428 | O68: =IFERROR(VLOOKUP($A68,RA_result!$B$3:$N$62,7,0),"") -> M | P68: =IFERROR(VLOOKUP($A68,RA_result!$B$3:$N$62,9,0),"") -> L | Q68: =IFERROR(VLOOKUP($A68,RA_result!$B$3:$N$62,10,0),"") | R68: N | S68: =IFERROR(VLOOKUP($A68,RA_result!$B$3:$N$62,4,0),"") -> 1.0535504e+09 | T68: 0.9 | U68: =IFERROR(IF(VLOOKUP($A68,RA_result!$B$3:$N$62,6,0)="",S68*T68,VLOOKUP($A68,RA_result!$B$3:$N$62,6,0)),"") -> 9.4819535e+08 | V68: 1.3 | W68: =IFERROR((S68*30%)/V68,0) -> 2.4312701e+08 | X68: =IFERROR(N68/W68,0) -> 0.016343013 | AA68: =IF(OR(U68="",Y68="",Z68=""),"",IF(AND(U68>Y68,-U68<Z68),"Ok","Not Ok"))
A69: =TB_audited!A52 -> Other long-term liability | D69: =TB_audited!B52 -> 22901 | E69: =TB_audited!C52 -> 350/0400 | F69: =TB_audited!D52 -> SALES DOWN PAYMENT (DEPOSIT IDR) | G69: =IF($D$8="Interim",TB_audited!G52,TB_audited!E52) -> 2775984576 | H69: =IFERROR(VLOOKUP($A69,RA_result!$B$3:$N$62,11,0),"") | I69: =IFERROR(VLOOKUP($A69,RA_result!$B$3:$N$62,12,0),"") -> Ya | J69: =IFERROR(VLOOKUP($A69,RA_result!$B$3:$N$62,13,0),"") -> YE | K69: Ya | L69: Tidak | M69: 2775984576 | N69: =G69-M69 -> 0 | O69: =IFERROR(VLOOKUP($A69,RA_result!$B$3:$N$62,7,0),"") -> M | P69: =IFERROR(VLOOKUP($A69,RA_result!$B$3:$N$62,9,0),"") -> L | Q69: =IFERROR(VLOOKUP($A69,RA_result!$B$3:$N$62,10,0),"") | R69: N | S69: =IFERROR(VLOOKUP($A69,RA_result!$B$3:$N$62,4,0),"") -> 1.0535504e+09 | T69: 0.9 | U69: =IFERROR(IF(VLOOKUP($A69,RA_result!$B$3:$N$62,6,0)="",S69*T69,VLOOKUP($A69,RA_result!$B$3:$N$62,6,0)),"") -> 9.4819535e+08 | V69: 1.3 | W69: =IFERROR((S69*30%)/V69,0) -> 2.4312701e+08 | X69: =IFERROR(N69/W69,0) -> 0 | AA69: =IF(OR(U69="",Y69="",Z69=""),"",IF(AND(U69>Y69,-U69<Z69),"Ok","Not Ok"))
A70: =TB_audited!A53 -> Other long-term liability | D70: =TB_audited!B53 -> 22902 | E70: =TB_audited!C53 -> 350/0800 | F70: =TB_audited!D53 -> SALES DOWN PAYMENT MKH | G70: =IF($D$8="Interim",TB_audited!G53,TB_audited!E53) -> 0 | H70: =IFERROR(VLOOKUP($A70,RA_result!$B$3:$N$62,11,0),"") | I70: =IFERROR(VLOOKUP($A70,RA_result!$B$3:$N$62,12,0),"") -> Ya | J70: =IFERROR(VLOOKUP($A70,RA_result!$B$3:$N$62,13,0),"") -> YE | M70: 0 | N70: =G70-M70 -> 0 | O70: =IFERROR(VLOOKUP($A70,RA_result!$B$3:$N$62,7,0),"") -> M | P70: =IFERROR(VLOOKUP($A70,RA_result!$B$3:$N$62,9,0),"") -> L | Q70: =IFERROR(VLOOKUP($A70,RA_result!$B$3:$N$62,10,0),"") | R70: N | S70: =IFERROR(VLOOKUP($A70,RA_result!$B$3:$N$62,4,0),"") -> 1.0535504e+09 | T70: 0.9 | U70: =IFERROR(IF(VLOOKUP($A70,RA_result!$B$3:$N$62,6,0)="",S70*T70,VLOOKUP($A70,RA_result!$B$3:$N$62,6,0)),"") -> 9.4819535e+08 | V70: 1.3 | W70: =IFERROR((S70*30%)/V70,0) -> 2.4312701e+08 | X70: =IFERROR(N70/W70,0) -> 0 | AA70: =IF(OR(U70="",Y70="",Z70=""),"",IF(AND(U70>Y70,-U70<Z70),"Ok","Not Ok"))
A71: =TB_audited!A54 -> Taxes payable | D71: =TB_audited!B54 -> 21701 | E71: =TB_audited!C54 -> 360/0030 | F71: =TB_audited!D54 -> PPH PASAL 23 ( WITHOLDING TAX ) | G71: =IF($D$8="Interim",TB_audited!G54,TB_audited!E54) -> 3085065 | H71: =IFERROR(VLOOKUP($A71,RA_result!$B$3:$N$62,11,0),"") | I71: =IFERROR(VLOOKUP($A71,RA_result!$B$3:$N$62,12,0),"") -> Ya | J71: =IFERROR(VLOOKUP($A71,RA_result!$B$3:$N$62,13,0),"") -> YE | K71: Ya | L71: Tidak | M71: 3085065 | N71: =G71-M71 -> 0 | O71: =IFERROR(VLOOKUP($A71,RA_result!$B$3:$N$62,7,0),"") -> M | P71: =IFERROR(VLOOKUP($A71,RA_result!$B$3:$N$62,9,0),"") -> L | Q71: =IFERROR(VLOOKUP($A71,RA_result!$B$3:$N$62,10,0),"") | R71: N | S71: =IFERROR(VLOOKUP($A71,RA_result!$B$3:$N$62,4,0),"") -> 1.0535504e+09 | T71: 0.9 | U71: =IFERROR(IF(VLOOKUP($A71,RA_result!$B$3:$N$62,6,0)="",S71*T71,VLOOKUP($A71,RA_result!$B$3:$N$62,6,0)),"") -> 2.9499411e+08 | V71: 1.3 | W71: =IFERROR((S71*30%)/V71,0) -> 2.4312701e+08 | X71: =IFERROR(N71/W71,0) -> 0 | AA71: =IF(OR(U71="",Y71="",Z71=""),"",IF(AND(U71>Y71,-U71<Z71),"Ok","Not Ok"))
A72: =TB_audited!A55 -> Taxes payable | D72: =TB_audited!B55 -> 21702 | E72: =TB_audited!C55 -> 360/0040 | F72: =TB_audited!D55 -> PPH PASAL 4 AYAT 2 KONSTRUKSI | G72: =IF($D$8="Interim",TB_audited!G55,TB_audited!E55) -> 0 | H72: =IFERROR(VLOOKUP($A72,RA_result!$B$3:$N$62,11,0),"") | I72: =IFERROR(VLOOKUP($A72,RA_result!$B$3:$N$62,12,0),"") -> Ya | J72: =IFERROR(VLOOKUP($A72,RA_result!$B$3:$N$62,13,0),"") -> YE | M72: 0 | N72: =G72-M72 -> 0 | O72: =IFERROR(VLOOKUP($A72,RA_result!$B$3:$N$62,7,0),"") -> M | P72: =IFERROR(VLOOKUP($A72,RA_result!$B$3:$N$62,9,0),"") -> L | Q72: =IFERROR(VLOOKUP($A72,RA_result!$B$3:$N$62,10,0),"") | R72: N | S72: =IFERROR(VLOOKUP($A72,RA_result!$B$3:$N$62,4,0),"") -> 1.0535504e+09 | T72: 0.9 | U72: =IFERROR(IF(VLOOKUP($A72,RA_result!$B$3:$N$62,6,0)="",S72*T72,VLOOKUP($A72,RA_result!$B$3:$N$62,6,0)),"") -> 2.9499411e+08 | V72: 1.3 | W72: =IFERROR((S72*30%)/V72,0) -> 2.4312701e+08 | X72: =IFERROR(N72/W72,0) -> 0 | AA72: =IF(OR(U72="",Y72="",Z72=""),"",IF(AND(U72>Y72,-U72<Z72),"Ok","Not Ok"))
A73: =TB_audited!A56 -> Taxes payable | D73: =TB_audited!B56 -> 21703 | E73: =TB_audited!C56 -> 360/0050 | F73: =TB_audited!D56 -> PPH PASAL 21 | G73: =IF($D$8="Interim",TB_audited!G56,TB_audited!E56) -> 0 | H73: =IFERROR(VLOOKUP($A73,RA_result!$B$3:$N$62,11,0),"") | I73: =IFERROR(VLOOKUP($A73,RA_result!$B$3:$N$62,12,0),"") -> Ya | J73: =IFERROR(VLOOKUP($A73,RA_result!$B$3:$N$62,13,0),"") -> YE | M73: 0 | N73: =G73-M73 -> 0 | O73: =IFERROR(VLOOKUP($A73,RA_result!$B$3:$N$62,7,0),"") -> M | P73: =IFERROR(VLOOKUP($A73,RA_result!$B$3:$N$62,9,0),"") -> L | Q73: =IFERROR(VLOOKUP($A73,RA_result!$B$3:$N$62,10,0),"") | R73: N | S73: =IFERROR(VLOOKUP($A73,RA_result!$B$3:$N$62,4,0),"") -> 1.0535504e+09 | T73: 0.9 | U73: =IFERROR(IF(VLOOKUP($A73,RA_result!$B$3:$N$62,6,0)="",S73*T73,VLOOKUP($A73,RA_result!$B$3:$N$62,6,0)),"") -> 2.9499411e+08 | V73: 1.3 | W73: =IFERROR((S73*30%)/V73,0) -> 2.4312701e+08 | X73: =IFERROR(N73/W73,0) -> 0 | AA73: =IF(OR(U73="",Y73="",Z73=""),"",IF(AND(U73>Y73,-U73<Z73),"Ok","Not Ok"))
A74: =TB_audited!A57 -> Taxes payable | D74: =TB_audited!B57 -> 21704 | E74: =TB_audited!C57 -> 360/0060 | F74: =TB_audited!D57 -> PPH PASAL 29 | G74: =IF($D$8="Interim",TB_audited!G57,TB_audited!E57) -> 0 | H74: =IFERROR(VLOOKUP($A74,RA_result!$B$3:$N$62,11,0),"") | I74: =IFERROR(VLOOKUP($A74,RA_result!$B$3:$N$62,12,0),"") -> Ya | J74: =IFERROR(VLOOKUP($A74,RA_result!$B$3:$N$62,13,0),"") -> YE | M74: 0 | N74: =G74-M74 -> 0 | O74: =IFERROR(VLOOKUP($A74,RA_result!$B$3:$N$62,7,0),"") -> M | P74: =IFERROR(VLOOKUP($A74,RA_result!$B$3:$N$62,9,0),"") -> L | Q74: =IFERROR(VLOOKUP($A74,RA_result!$B$3:$N$62,10,0),"") | R74: N | S74: =IFERROR(VLOOKUP($A74,RA_result!$B$3:$N$62,4,0),"") -> 1.0535504e+09 | T74: 0.9 | U74: =IFERROR(IF(VLOOKUP($A74,RA_result!$B$3:$N$62,6,0)="",S74*T74,VLOOKUP($A74,RA_result!$B$3:$N$62,6,0)),"") -> 2.9499411e+08 | V74: 1.3 | W74: =IFERROR((S74*30%)/V74,0) -> 2.4312701e+08 | X74: =IFERROR(N74/W74,0) -> 0 | AA74: =IF(OR(U74="",Y74="",Z74=""),"",IF(AND(U74>Y74,-U74<Z74),"Ok","Not Ok"))
A75: =TB_audited!A58 -> Taxes payable | D75: =TB_audited!B58 -> 21705 | E75: =TB_audited!C58 -> 360/0070 | F75: =TB_audited!D58 -> PPH PASAL 25 | G75: =IF($D$8="Interim",TB_audited!G58,TB_audited!E58) -> 402433766 | H75: =IFERROR(VLOOKUP($A75,RA_result!$B$3:$N$62,11,0),"") | I75: =IFERROR(VLOOKUP($A75,RA_result!$B$3:$N$62,12,0),"") -> Ya | J75: =IFERROR(VLOOKUP($A75,RA_result!$B$3:$N$62,13,0),"") -> YE | K75: Ya | L75: Tidak | M75: 402433766 | N75: =G75-M75 -> 0 | O75: =IFERROR(VLOOKUP($A75,RA_result!$B$3:$N$62,7,0),"") -> M | P75: =IFERROR(VLOOKUP($A75,RA_result!$B$3:$N$62,9,0),"") -> L | Q75: =IFERROR(VLOOKUP($A75,RA_result!$B$3:$N$62,10,0),"") | R75: N | S75: =IFERROR(VLOOKUP($A75,RA_result!$B$3:$N$62,4,0),"") -> 1.0535504e+09 | T75: 0.9 | U75: =IFERROR(IF(VLOOKUP($A75,RA_result!$B$3:$N$62,6,0)="",S75*T75,VLOOKUP($A75,RA_result!$B$3:$N$62,6,0)),"") -> 2.9499411e+08 | V75: 1.3 | W75: =IFERROR((S75*30%)/V75,0) -> 2.4312701e+08 | X75: =IFERROR(N75/W75,0) -> 0 | AA75: =IF(OR(U75="",Y75="",Z75=""),"",IF(AND(U75>Y75,-U75<Z75),"Ok","Not Ok"))
A76: =TB_audited!A59 -> Taxes payable | D76: =TB_audited!B59 -> 21706 | E76: =TB_audited!C59 -> 360/0080 | F76: =TB_audited!D59 -> VAT ( OUT VS IN ) | G76: =IF($D$8="Interim",TB_audited!G59,TB_audited!E59) -> 95663390 | H76: =IFERROR(VLOOKUP($A76,RA_result!$B$3:$N$62,11,0),"") | I76: =IFERROR(VLOOKUP($A76,RA_result!$B$3:$N$62,12,0),"") -> Ya | J76: =IFERROR(VLOOKUP($A76,RA_result!$B$3:$N$62,13,0),"") -> YE | K76: Ya | L76: Tidak | M76: 95663390 | N76: =G76-M76 -> 0 | O76: =IFERROR(VLOOKUP($A76,RA_result!$B$3:$N$62,7,0),"") -> M | P76: =IFERROR(VLOOKUP($A76,RA_result!$B$3:$N$62,9,0),"") -> L | Q76: =IFERROR(VLOOKUP($A76,RA_result!$B$3:$N$62,10,0),"") | R76: N | S76: =IFERROR(VLOOKUP($A76,RA_result!$B$3:$N$62,4,0),"") -> 1.0535504e+09 | T76: 0.9 | U76: =IFERROR(IF(VLOOKUP($A76,RA_result!$B$3:$N$62,6,0)="",S76*T76,VLOOKUP($A76,RA_result!$B$3:$N$62,6,0)),"") -> 2.9499411e+08 | V76: 1.3 | W76: =IFERROR((S76*30%)/V76,0) -> 2.4312701e+08 | X76: =IFERROR(N76/W76,0) -> 0 | AA76: =IF(OR(U76="",Y76="",Z76=""),"",IF(AND(U76>Y76,-U76<Z76),"Ok","Not Ok"))
A77: =TB_audited!A60 -> Share capital | D77: =TB_audited!B60 -> 31101 | E77: =TB_audited!C60 -> 400/0000 | F77: =TB_audited!D60 -> CAPITAL | G77: =IF($D$8="Interim",TB_audited!G60,TB_audited!E60) -> 10500000000 | H77: =IFERROR(VLOOKUP($A77,RA_result!$B$3:$N$62,11,0),"") | I77: =IFERROR(VLOOKUP($A77,RA_result!$B$3:$N$62,12,0),"") -> Ya | J77: =IFERROR(VLOOKUP($A77,RA_result!$B$3:$N$62,13,0),"") -> YE | K77: Ya | L77: Tidak | M77: 10500000000 | N77: =G77-M77 -> 0 | O77: =IFERROR(VLOOKUP($A77,RA_result!$B$3:$N$62,7,0),"") -> M | P77: =IFERROR(VLOOKUP($A77,RA_result!$B$3:$N$62,9,0),"") -> L | Q77: =IFERROR(VLOOKUP($A77,RA_result!$B$3:$N$62,10,0),"") | R77: N | S77: =IFERROR(VLOOKUP($A77,RA_result!$B$3:$N$62,4,0),"") -> 1.0535504e+09 | T77: 0.9 | U77: =IFERROR(IF(VLOOKUP($A77,RA_result!$B$3:$N$62,6,0)="",S77*T77,VLOOKUP($A77,RA_result!$B$3:$N$62,6,0)),"") -> 9.4819535e+08 | V77: 1.3 | W77: =IFERROR((S77*30%)/V77,0) -> 2.4312701e+08 | X77: =IFERROR(N77/W77,0) -> 0 | AA77: =IF(OR(U77="",Y77="",Z77=""),"",IF(AND(U77>Y77,-U77<Z77),"Ok","Not Ok"))
A78: =TB_audited!A61 -> Retained earnings – unappropriated | D78: =TB_audited!B61 -> 33201 | E78: =TB_audited!C61 -> 410/0000 | F78: =TB_audited!D61 -> RETAINED EARNINGS | G78: =IF($D$8="Interim",TB_audited!G61,TB_audited!E61) -> 31480858157 | H78: =IFERROR(VLOOKUP($A78,RA_result!$B$3:$N$62,11,0),"") | I78: =IFERROR(VLOOKUP($A78,RA_result!$B$3:$N$62,12,0),"") -> Ya | J78: =IFERROR(VLOOKUP($A78,RA_result!$B$3:$N$62,13,0),"") -> YE | K78: Ya | L78: Tidak | M78: 31480858157 | N78: =G78-M78 -> 0 | O78: =IFERROR(VLOOKUP($A78,RA_result!$B$3:$N$62,7,0),"") -> M | P78: =IFERROR(VLOOKUP($A78,RA_result!$B$3:$N$62,9,0),"") -> L | Q78: =IFERROR(VLOOKUP($A78,RA_result!$B$3:$N$62,10,0),"") | R78: N | S78: =IFERROR(VLOOKUP($A78,RA_result!$B$3:$N$62,4,0),"") -> 1.0535504e+09 | T78: 0.9 | U78: =IFERROR(IF(VLOOKUP($A78,RA_result!$B$3:$N$62,6,0)="",S78*T78,VLOOKUP($A78,RA_result!$B$3:$N$62,6,0)),"") -> 9.4819535e+08 | V78: 1.3 | W78: =IFERROR((S78*30%)/V78,0) -> 2.4312701e+08 | X78: =IFERROR(N78/W78,0) -> 0 | AA78: =IF(OR(U78="",Y78="",Z78=""),"",IF(AND(U78>Y78,-U78<Z78),"Ok","Not Ok"))
A79: =TB_audited!A62 -> Revenue | D79: =TB_audited!B62 -> 41101 | E79: =TB_audited!C62 -> 500/0010 | F79: =TB_audited!D62 -> SALES-PROJECT, ECT | G79: =IF($D$8="Interim",TB_audited!G62,TB_audited!E62) -> 4390382740 | H79: =IFERROR(VLOOKUP($A79,RA_result!$B$3:$N$62,11,0),"") | I79: =IFERROR(VLOOKUP($A79,RA_result!$B$3:$N$62,12,0),"") -> Ya | J79: =IFERROR(VLOOKUP($A79,RA_result!$B$3:$N$62,13,0),"") -> YE | K79: Ya | L79: Tidak | M79: 4390382740 | N79: =G79-M79 -> 0 | O79: =IFERROR(VLOOKUP($A79,RA_result!$B$3:$N$62,7,0),"") -> M | P79: =IFERROR(VLOOKUP($A79,RA_result!$B$3:$N$62,9,0),"") -> H | Q79: =IFERROR(VLOOKUP($A79,RA_result!$B$3:$N$62,10,0),"") | R79: N | S79: =IFERROR(VLOOKUP($A79,RA_result!$B$3:$N$62,4,0),"") -> 1.0535504e+09 | T79: 0.9 | U79: =IFERROR(IF(VLOOKUP($A79,RA_result!$B$3:$N$62,6,0)="",S79*T79,VLOOKUP($A79,RA_result!$B$3:$N$62,6,0)),"") -> 9.4819535e+08 | V79: 1.6 | W79: =IFERROR((S79*30%)/V79,0) -> 1.975407e+08 | X79: =IFERROR(N79/W79,0) -> 0 | AA79: =IF(OR(U79="",Y79="",Z79=""),"",IF(AND(U79>Y79,-U79<Z79),"Ok","Not Ok"))
A80: =TB_audited!A63 -> Revenue | D80: =TB_audited!B63 -> 41102 | E80: =TB_audited!C63 -> 500/0020 | F80: =TB_audited!D63 -> SALES-SPAREPARTS | G80: =IF($D$8="Interim",TB_audited!G63,TB_audited!E63) -> 5.914664e+10 | H80: =IFERROR(VLOOKUP($A80,RA_result!$B$3:$N$62,11,0),"") | I80: =IFERROR(VLOOKUP($A80,RA_result!$B$3:$N$62,12,0),"") -> Ya | J80: =IFERROR(VLOOKUP($A80,RA_result!$B$3:$N$62,13,0),"") -> YE | K80: Tidak | L80: Ya | M80: 1.0030952e+10 | N80: =G80-M80 -> 4.9115689e+10 | O80: =IFERROR(VLOOKUP($A80,RA_result!$B$3:$N$62,7,0),"") -> M | P80: =IFERROR(VLOOKUP($A80,RA_result!$B$3:$N$62,9,0),"") -> H | Q80: =IFERROR(VLOOKUP($A80,RA_result!$B$3:$N$62,10,0),"") | R80: N | S80: =IFERROR(VLOOKUP($A80,RA_result!$B$3:$N$62,4,0),"") -> 1.0535504e+09 | T80: 0.9 | U80: =IFERROR(IF(VLOOKUP($A80,RA_result!$B$3:$N$62,6,0)="",S80*T80,VLOOKUP($A80,RA_result!$B$3:$N$62,6,0)),"") -> 9.4819535e+08 | V80: 1.9 | W80: =IFERROR((S80*30%)/V80,0) -> 1.6635006e+08 | X80: =IFERROR(N80/W80,0) -> 295.25501 | Y80: 6.8761964e+08 | Z80: -6.8761964e+08 | AA80: =IF(OR(U80="",Y80="",Z80=""),"",IF(AND(U80>Y80,-U80<Z80),"Ok","Not Ok")) -> Ok
A81: =TB_audited!A64 -> Revenue | D81: =TB_audited!B64 -> 41103 | E81: =TB_audited!C64 -> 500/0030 | F81: =TB_audited!D64 -> SALES-MACHINE | G81: =IF($D$8="Interim",TB_audited!G64,TB_audited!E64) -> 17703000000 | H81: =IFERROR(VLOOKUP($A81,RA_result!$B$3:$N$62,11,0),"") | I81: =IFERROR(VLOOKUP($A81,RA_result!$B$3:$N$62,12,0),"") -> Ya | J81: =IFERROR(VLOOKUP($A81,RA_result!$B$3:$N$62,13,0),"") -> YE | K81: Ya | L81: Tidak | M81: 17703000000 | N81: =G81-M81 -> 0 | O81: =IFERROR(VLOOKUP($A81,RA_result!$B$3:$N$62,7,0),"") -> M | P81: =IFERROR(VLOOKUP($A81,RA_result!$B$3:$N$62,9,0),"") -> H | Q81: =IFERROR(VLOOKUP($A81,RA_result!$B$3:$N$62,10,0),"") | R81: N | S81: =IFERROR(VLOOKUP($A81,RA_result!$B$3:$N$62,4,0),"") -> 1.0535504e+09 | T81: 0.9 | U81: =IFERROR(IF(VLOOKUP($A81,RA_result!$B$3:$N$62,6,0)="",S81*T81,VLOOKUP($A81,RA_result!$B$3:$N$62,6,0)),"") -> 9.4819535e+08 | V81: 1.6 | W81: =IFERROR((S81*30%)/V81,0) -> 1.975407e+08 | X81: =IFERROR(N81/W81,0) -> 0 | AA81: =IF(OR(U81="",Y81="",Z81=""),"",IF(AND(U81>Y81,-U81<Z81),"Ok","Not Ok"))
A82: =TB_audited!A65 -> Revenue | D82: =TB_audited!B65 -> 41104 | E82: =TB_audited!C65 -> 500/0041 | F82: =TB_audited!D65 -> SALES-SERVICES AND MAINTENANCE | G82: =IF($D$8="Interim",TB_audited!G65,TB_audited!E65) -> 2193044276 | H82: =IFERROR(VLOOKUP($A82,RA_result!$B$3:$N$62,11,0),"") | I82: =IFERROR(VLOOKUP($A82,RA_result!$B$3:$N$62,12,0),"") -> Ya | J82: =IFERROR(VLOOKUP($A82,RA_result!$B$3:$N$62,13,0),"") -> YE | K82: Tidak | L82: Ya | M82: 1242662000 | N82: =G82-M82 -> 950382276 | O82: =IFERROR(VLOOKUP($A82,RA_result!$B$3:$N$62,7,0),"") -> M | P82: =IFERROR(VLOOKUP($A82,RA_result!$B$3:$N$62,9,0),"") -> H | Q82: =IFERROR(VLOOKUP($A82,RA_result!$B$3:$N$62,10,0),"") | R82: N | S82: =IFERROR(VLOOKUP($A82,RA_result!$B$3:$N$62,4,0),"") -> 1.0535504e+09 | T82: 0.9 | U82: =IFERROR(IF(VLOOKUP($A82,RA_result!$B$3:$N$62,6,0)="",S82*T82,VLOOKUP($A82,RA_result!$B$3:$N$62,6,0)),"") -> 9.4819535e+08 | V82: 1.9 | W82: =IFERROR((S82*30%)/V82,0) -> 1.6635006e+08 | X82: =IFERROR(N82/W82,0) -> 5.7131465 | Y82: 1.0359167e+08 | Z82: -1.0359167e+08 | AA82: =IF(OR(U82="",Y82="",Z82=""),"",IF(AND(U82>Y82,-U82<Z82),"Ok","Not Ok")) -> Ok
A83: =TB_audited!A66 -> Revenue | D83: =TB_audited!B66 -> 41105 | E83: =TB_audited!C66 -> 560/0000 | F83: =TB_audited!D66 -> RETURN OUTWARDS (SALES RETURN) | G83: =IF($D$8="Interim",TB_audited!G66,TB_audited!E66) -> -15500000 | H83: =IFERROR(VLOOKUP($A83,RA_result!$B$3:$N$62,11,0),"") | I83: =IFERROR(VLOOKUP($A83,RA_result!$B$3:$N$62,12,0),"") -> Ya | J83: =IFERROR(VLOOKUP($A83,RA_result!$B$3:$N$62,13,0),"") -> YE | K83: Ya | L83: Tidak | M83: -15500000 | N83: =G83-M83 -> 0 | O83: =IFERROR(VLOOKUP($A83,RA_result!$B$3:$N$62,7,0),"") -> M | P83: =IFERROR(VLOOKUP($A83,RA_result!$B$3:$N$62,9,0),"") -> H | Q83: =IFERROR(VLOOKUP($A83,RA_result!$B$3:$N$62,10,0),"") | R83: N | S83: =IFERROR(VLOOKUP($A83,RA_result!$B$3:$N$62,4,0),"") -> 1.0535504e+09 | T83: 0.9 | U83: =IFERROR(IF(VLOOKUP($A83,RA_result!$B$3:$N$62,6,0)="",S83*T83,VLOOKUP($A83,RA_result!$B$3:$N$62,6,0)),"") -> 9.4819535e+08 | V83: 1.6 | W83: =IFERROR((S83*30%)/V83,0) -> 1.975407e+08 | X83: =IFERROR(N83/W83,0) -> 0 | AA83: =IF(OR(U83="",Y83="",Z83=""),"",IF(AND(U83>Y83,-U83<Z83),"Ok","Not Ok"))
A84: =TB_audited!A67 -> Cost of revenue | D84: =TB_audited!B67 -> 51101 | E84: =TB_audited!C67 -> 600/0010 | F84: =TB_audited!D67 -> OPENING STOCKS-STOCKS-MACHINE | G84: =IF($D$8="Interim",TB_audited!G67,TB_audited!E67) -> 333000000 | H84: =IFERROR(VLOOKUP($A84,RA_result!$B$3:$N$62,11,0),"") | I84: =IFERROR(VLOOKUP($A84,RA_result!$B$3:$N$62,12,0),"") -> Ya | J84: =IFERROR(VLOOKUP($A84,RA_result!$B$3:$N$62,13,0),"") -> YE | M84: 333000000 | N84: =G84-M84 -> 0 | O84: =IFERROR(VLOOKUP($A84,RA_result!$B$3:$N$62,7,0),"") -> M | P84: =IFERROR(VLOOKUP($A84,RA_result!$B$3:$N$62,9,0),"") -> L | Q84: =IFERROR(VLOOKUP($A84,RA_result!$B$3:$N$62,10,0),"") | R84: N | S84: =IFERROR(VLOOKUP($A84,RA_result!$B$3:$N$62,4,0),"") -> 1.0535504e+09 | T84: 0.9 | U84: =IFERROR(IF(VLOOKUP($A84,RA_result!$B$3:$N$62,6,0)="",S84*T84,VLOOKUP($A84,RA_result!$B$3:$N$62,6,0)),"") -> 9.4819535e+08 | V84: 1.3 | W84: =IFERROR((S84*30%)/V84,0) -> 2.4312701e+08 | X84: =IFERROR(N84/W84,0) -> 0 | AA84: =IF(OR(U84="",Y84="",Z84=""),"",IF(AND(U84>Y84,-U84<Z84),"Ok","Not Ok"))
A85: =TB_audited!A68 -> Cost of revenue | D85: =TB_audited!B68 -> 51102 | E85: =TB_audited!C68 -> 600/0020 | F85: =TB_audited!D68 -> OPENING STOCKS-STOCKS-SPAREPARTS | G85: =IF($D$8="Interim",TB_audited!G68,TB_audited!E68) -> 9.8969615e+09 | H85: =IFERROR(VLOOKUP($A85,RA_result!$B$3:$N$62,11,0),"") | I85: =IFERROR(VLOOKUP($A85,RA_result!$B$3:$N$62,12,0),"") -> Ya | J85: =IFERROR(VLOOKUP($A85,RA_result!$B$3:$N$62,13,0),"") -> YE | M85: 9.8969615e+09 | N85: =G85-M85 -> 0 | O85: =IFERROR(VLOOKUP($A85,RA_result!$B$3:$N$62,7,0),"") -> M | P85: =IFERROR(VLOOKUP($A85,RA_result!$B$3:$N$62,9,0),"") -> L | Q85: =IFERROR(VLOOKUP($A85,RA_result!$B$3:$N$62,10,0),"") | R85: N | S85: =IFERROR(VLOOKUP($A85,RA_result!$B$3:$N$62,4,0),"") -> 1.0535504e+09 | T85: 0.9 | U85: =IFERROR(IF(VLOOKUP($A85,RA_result!$B$3:$N$62,6,0)="",S85*T85,VLOOKUP($A85,RA_result!$B$3:$N$62,6,0)),"") -> 9.4819535e+08 | V85: 1.3 | W85: =IFERROR((S85*30%)/V85,0) -> 2.4312701e+08 | X85: =IFERROR(N85/W85,0) -> 0 | AA85: =IF(OR(U85="",Y85="",Z85=""),"",IF(AND(U85>Y85,-U85<Z85),"Ok","Not Ok"))
A86: =TB_audited!A69 -> Cost of revenue | D86: =TB_audited!B69 -> 51103 | E86: =TB_audited!C69 -> 610/0010 | F86: =TB_audited!D69 -> PURCHASES-SPREPARTS | G86: =IF($D$8="Interim",TB_audited!G69,TB_audited!E69) -> 3.6720071e+10 | H86: =IFERROR(VLOOKUP($A86,RA_result!$B$3:$N$62,11,0),"") | I86: =IFERROR(VLOOKUP($A86,RA_result!$B$3:$N$62,12,0),"") -> Ya | J86: =IFERROR(VLOOKUP($A86,RA_result!$B$3:$N$62,13,0),"") -> YE | K86: Tidak | L86: Ya | M86: 10360954373 | N86: =G86-M86 -> 2.6359116e+10 | O86: =IFERROR(VLOOKUP($A86,RA_result!$B$3:$N$62,7,0),"") -> M | P86: =IFERROR(VLOOKUP($A86,RA_result!$B$3:$N$62,9,0),"") -> L | Q86: =IFERROR(VLOOKUP($A86,RA_result!$B$3:$N$62,10,0),"") | R86: N | S86: =IFERROR(VLOOKUP($A86,RA_result!$B$3:$N$62,4,0),"") -> 1.0535504e+09 | T86: 0.9 | U86: =IFERROR(IF(VLOOKUP($A86,RA_result!$B$3:$N$62,6,0)="",S86*T86,VLOOKUP($A86,RA_result!$B$3:$N$62,6,0)),"") -> 9.4819535e+08 | V86: 1.4 | W86: =IFERROR((S86*30%)/V86,0) -> 2.257608e+08 | X86: =IFERROR(N86/W86,0) -> 116.75684 | Y86: 6.0625968e+08 | Z86: -6.0625968e+08 | AA86: =IF(OR(U86="",Y86="",Z86=""),"",IF(AND(U86>Y86,-U86<Z86),"Ok","Not Ok")) -> Ok
A87: =TB_audited!A70 -> Cost of revenue | D87: =TB_audited!B70 -> 51104 | E87: =TB_audited!C70 -> 610/0020 | F87: =TB_audited!D70 -> PURCHASES-MACHINES | G87: =IF($D$8="Interim",TB_audited!G70,TB_audited!E70) -> 1.4380361e+10 | H87: =IFERROR(VLOOKUP($A87,RA_result!$B$3:$N$62,11,0),"") | I87: =IFERROR(VLOOKUP($A87,RA_result!$B$3:$N$62,12,0),"") -> Ya | J87: =IFERROR(VLOOKUP($A87,RA_result!$B$3:$N$62,13,0),"") -> YE | K87: Tidak | L87: Ya | M87: 1.4380361e+10 | N87: =G87-M87 -> 0 | O87: =IFERROR(VLOOKUP($A87,RA_result!$B$3:$N$62,7,0),"") -> M | P87: =IFERROR(VLOOKUP($A87,RA_result!$B$3:$N$62,9,0),"") -> L | Q87: =IFERROR(VLOOKUP($A87,RA_result!$B$3:$N$62,10,0),"") | R87: N | S87: =IFERROR(VLOOKUP($A87,RA_result!$B$3:$N$62,4,0),"") -> 1.0535504e+09 | T87: 0.9 | U87: =IFERROR(IF(VLOOKUP($A87,RA_result!$B$3:$N$62,6,0)="",S87*T87,VLOOKUP($A87,RA_result!$B$3:$N$62,6,0)),"") -> 9.4819535e+08 | V87: 1.3 | W87: =IFERROR((S87*30%)/V87,0) -> 2.4312701e+08 | X87: =IFERROR(N87/W87,0) -> 0 | AA87: =IF(OR(U87="",Y87="",Z87=""),"",IF(AND(U87>Y87,-U87<Z87),"Ok","Not Ok"))
A88: =TB_audited!A71 -> Cost of revenue | D88: =TB_audited!B71 -> 51105 | E88: =TB_audited!C71 -> 610/0040 | F88: =TB_audited!D71 -> PURCHASES-PROJECT,ETC | G88: =IF($D$8="Interim",TB_audited!G71,TB_audited!E71) -> 3030023431 | H88: =IFERROR(VLOOKUP($A88,RA_result!$B$3:$N$62,11,0),"") | I88: =IFERROR(VLOOKUP($A88,RA_result!$B$3:$N$62,12,0),"") -> Ya | J88: =IFERROR(VLOOKUP($A88,RA_result!$B$3:$N$62,13,0),"") -> YE | K88: Ya | L88: Tidak | M88: 3030023431 | N88: =G88-M88 -> 0 | O88: =IFERROR(VLOOKUP($A88,RA_result!$B$3:$N$62,7,0),"") -> M | P88: =IFERROR(VLOOKUP($A88,RA_result!$B$3:$N$62,9,0),"") -> L | Q88: =IFERROR(VLOOKUP($A88,RA_result!$B$3:$N$62,10,0),"") | R88: N | S88: =IFERROR(VLOOKUP($A88,RA_result!$B$3:$N$62,4,0),"") -> 1.0535504e+09 | T88: 0.9 | U88: =IFERROR(IF(VLOOKUP($A88,RA_result!$B$3:$N$62,6,0)="",S88*T88,VLOOKUP($A88,RA_result!$B$3:$N$62,6,0)),"") -> 9.4819535e+08 | V88: 1.3 | W88: =IFERROR((S88*30%)/V88,0) -> 2.4312701e+08 | X88: =IFERROR(N88/W88,0) -> 0 | AA88: =IF(OR(U88="",Y88="",Z88=""),"",IF(AND(U88>Y88,-U88<Z88),"Ok","Not Ok"))
A89: =TB_audited!A72 -> Cost of revenue | D89: =TB_audited!B72 -> 51106 | E89: =TB_audited!C72 -> 610/0050 | F89: =TB_audited!D72 -> PURCHASES-SERVICES AND MAINTENANCE | G89: =IF($D$8="Interim",TB_audited!G72,TB_audited!E72) -> 19730200 | H89: =IFERROR(VLOOKUP($A89,RA_result!$B$3:$N$62,11,0),"") | I89: =IFERROR(VLOOKUP($A89,RA_result!$B$3:$N$62,12,0),"") -> Ya | J89: =IFERROR(VLOOKUP($A89,RA_result!$B$3:$N$62,13,0),"") -> YE | K89: Tidak | L89: Ya | M89: 19730200 | N89: =G89-M89 -> 0 | O89: =IFERROR(VLOOKUP($A89,RA_result!$B$3:$N$62,7,0),"") -> M | P89: =IFERROR(VLOOKUP($A89,RA_result!$B$3:$N$62,9,0),"") -> L | Q89: =IFERROR(VLOOKUP($A89,RA_result!$B$3:$N$62,10,0),"") | R89: N | S89: =IFERROR(VLOOKUP($A89,RA_result!$B$3:$N$62,4,0),"") -> 1.0535504e+09 | T89: 0.9 | U89: =IFERROR(IF(VLOOKUP($A89,RA_result!$B$3:$N$62,6,0)="",S89*T89,VLOOKUP($A89,RA_result!$B$3:$N$62,6,0)),"") -> 9.4819535e+08 | V89: 1.3 | W89: =IFERROR((S89*30%)/V89,0) -> 2.4312701e+08 | X89: =IFERROR(N89/W89,0) -> 0 | AA89: =IF(OR(U89="",Y89="",Z89=""),"",IF(AND(U89>Y89,-U89<Z89),"Ok","Not Ok"))
A90: =TB_audited!A73 -> Cost of revenue | D90: =TB_audited!B73 -> 51107 | E90: =TB_audited!C73 -> 619/0010 | F90: =TB_audited!D73 -> CLOSING STOCKS-STOCKS-MACHINE | G90: =IF($D$8="Interim",TB_audited!G73,TB_audited!E73) -> -333000000 | H90: =IFERROR(VLOOKUP($A90,RA_result!$B$3:$N$62,11,0),"") | I90: =IFERROR(VLOOKUP($A90,RA_result!$B$3:$N$62,12,0),"") -> Ya | J90: =IFERROR(VLOOKUP($A90,RA_result!$B$3:$N$62,13,0),"") -> YE | M90: -333000000 | N90: =G90-M90 -> 0 | O90: =IFERROR(VLOOKUP($A90,RA_result!$B$3:$N$62,7,0),"") -> M | P90: =IFERROR(VLOOKUP($A90,RA_result!$B$3:$N$62,9,0),"") -> L | Q90: =IFERROR(VLOOKUP($A90,RA_result!$B$3:$N$62,10,0),"") | R90: N | S90: =IFERROR(VLOOKUP($A90,RA_result!$B$3:$N$62,4,0),"") -> 1.0535504e+09 | T90: 0.9 | U90: =IFERROR(IF(VLOOKUP($A90,RA_result!$B$3:$N$62,6,0)="",S90*T90,VLOOKUP($A90,RA_result!$B$3:$N$62,6,0)),"") -> 9.4819535e+08 | V90: 1.3 | W90: =IFERROR((S90*30%)/V90,0) -> 2.4312701e+08 | X90: =IFERROR(N90/W90,0) -> 0 | AA90: =IF(OR(U90="",Y90="",Z90=""),"",IF(AND(U90>Y90,-U90<Z90),"Ok","Not Ok"))
A91: =TB_audited!A74 -> Cost of revenue | D91: =TB_audited!B74 -> 51108 | E91: =TB_audited!C74 -> 619/0020 | F91: =TB_audited!D74 -> CLOSING STOCKS-STOCKS-SPAREPARTS | G91: =IF($D$8="Interim",TB_audited!G74,TB_audited!E74) -> -1.3896503e+10 | H91: =IFERROR(VLOOKUP($A91,RA_result!$B$3:$N$62,11,0),"") | I91: =IFERROR(VLOOKUP($A91,RA_result!$B$3:$N$62,12,0),"") -> Ya | J91: =IFERROR(VLOOKUP($A91,RA_result!$B$3:$N$62,13,0),"") -> YE | M91: -1.3896503e+10 | N91: =G91-M91 -> 0 | O91: =IFERROR(VLOOKUP($A91,RA_result!$B$3:$N$62,7,0),"") -> M | P91: =IFERROR(VLOOKUP($A91,RA_result!$B$3:$N$62,9,0),"") -> L | Q91: =IFERROR(VLOOKUP($A91,RA_result!$B$3:$N$62,10,0),"") | R91: N | S91: =IFERROR(VLOOKUP($A91,RA_result!$B$3:$N$62,4,0),"") -> 1.0535504e+09 | T91: 0.9 | U91: =IFERROR(IF(VLOOKUP($A91,RA_result!$B$3:$N$62,6,0)="",S91*T91,VLOOKUP($A91,RA_result!$B$3:$N$62,6,0)),"") -> 9.4819535e+08 | V91: 1.3 | W91: =IFERROR((S91*30%)/V91,0) -> 2.4312701e+08 | X91: =IFERROR(N91/W91,0) -> 0 | AA91: =IF(OR(U91="",Y91="",Z91=""),"",IF(AND(U91>Y91,-U91<Z91),"Ok","Not Ok"))
A92: =TB_audited!A75 -> Cost of revenue | D92: =TB_audited!B75 -> 51109 | E92: =TB_audited!C75 -> 620/0020 | F92: =TB_audited!D75 -> CUSTOM CLEARANCE EXPENSE | G92: =IF($D$8="Interim",TB_audited!G75,TB_audited!E75) -> 9.370446e+08 | H92: =IFERROR(VLOOKUP($A92,RA_result!$B$3:$N$62,11,0),"") | I92: =IFERROR(VLOOKUP($A92,RA_result!$B$3:$N$62,12,0),"") -> Ya | J92: =IFERROR(VLOOKUP($A92,RA_result!$B$3:$N$62,13,0),"") -> YE | M92: 9.370446e+08 | N92: =G92-M92 -> 0 | O92: =IFERROR(VLOOKUP($A92,RA_result!$B$3:$N$62,7,0),"") -> M | P92: =IFERROR(VLOOKUP($A92,RA_result!$B$3:$N$62,9,0),"") -> L | Q92: =IFERROR(VLOOKUP($A92,RA_result!$B$3:$N$62,10,0),"") | R92: N | S92: =IFERROR(VLOOKUP($A92,RA_result!$B$3:$N$62,4,0),"") -> 1.0535504e+09 | T92: 0.9 | U92: =IFERROR(IF(VLOOKUP($A92,RA_result!$B$3:$N$62,6,0)="",S92*T92,VLOOKUP($A92,RA_result!$B$3:$N$62,6,0)),"") -> 9.4819535e+08 | V92: 1.3 | W92: =IFERROR((S92*30%)/V92,0) -> 2.4312701e+08 | X92: =IFERROR(N92/W92,0) -> 0 | AA92: =IF(OR(U92="",Y92="",Z92=""),"",IF(AND(U92>Y92,-U92<Z92),"Ok","Not Ok"))
A93: =TB_audited!A76 -> Cost of revenue | D93: =TB_audited!B76 -> 51110 | E93: =TB_audited!C76 -> 650/0010 | F93: =TB_audited!D76 -> DEPRECIATION EXPENSE OF MACHINERY & EQUIPMENT | G93: =IF($D$8="Interim",TB_audited!G76,TB_audited!E76) -> 1952868 | H93: =IFERROR(VLOOKUP($A93,RA_result!$B$3:$N$62,11,0),"") | I93: =IFERROR(VLOOKUP($A93,RA_result!$B$3:$N$62,12,0),"") -> Ya | J93: =IFERROR(VLOOKUP($A93,RA_result!$B$3:$N$62,13,0),"") -> YE | M93: 1952868 | N93: =G93-M93 -> 0 | O93: =IFERROR(VLOOKUP($A93,RA_result!$B$3:$N$62,7,0),"") -> M | P93: =IFERROR(VLOOKUP($A93,RA_result!$B$3:$N$62,9,0),"") -> L | Q93: =IFERROR(VLOOKUP($A93,RA_result!$B$3:$N$62,10,0),"") | R93: N | S93: =IFERROR(VLOOKUP($A93,RA_result!$B$3:$N$62,4,0),"") -> 1.0535504e+09 | T93: 0.9 | U93: =IFERROR(IF(VLOOKUP($A93,RA_result!$B$3:$N$62,6,0)="",S93*T93,VLOOKUP($A93,RA_result!$B$3:$N$62,6,0)),"") -> 9.4819535e+08 | V93: 1.3 | W93: =IFERROR((S93*30%)/V93,0) -> 2.4312701e+08 | X93: =IFERROR(N93/W93,0) -> 0 | AA93: =IF(OR(U93="",Y93="",Z93=""),"",IF(AND(U93>Y93,-U93<Z93),"Ok","Not Ok"))
A94: =TB_audited!A77 -> Other expenses besides interest expense | D94: =TB_audited!B77 -> 53201 | E94: =TB_audited!C77 -> 810/0020 | F94: =TB_audited!D77 -> GAIN / ( LOSS) ON FOREIGN EXCHANGE FROM CREDITORS | G94: =IF($D$8="Interim",TB_audited!G77,TB_audited!E77) -> 6.7379325e+08 | H94: =IFERROR(VLOOKUP($A94,RA_result!$B$3:$N$62,11,0),"") | I94: =IFERROR(VLOOKUP($A94,RA_result!$B$3:$N$62,12,0),"") -> Ya | J94: =IFERROR(VLOOKUP($A94,RA_result!$B$3:$N$62,13,0),"") -> YE | K94: Tidak | L94: Ya | M94: 6.7379325e+08 | N94: =G94-M94 -> 0 | O94: =IFERROR(VLOOKUP($A94,RA_result!$B$3:$N$62,7,0),"") -> M | P94: =IFERROR(VLOOKUP($A94,RA_result!$B$3:$N$62,9,0),"") -> L | Q94: =IFERROR(VLOOKUP($A94,RA_result!$B$3:$N$62,10,0),"") | R94: N | S94: =IFERROR(VLOOKUP($A94,RA_result!$B$3:$N$62,4,0),"") -> 1.0535504e+09 | T94: 0.9 | U94: =IFERROR(IF(VLOOKUP($A94,RA_result!$B$3:$N$62,6,0)="",S94*T94,VLOOKUP($A94,RA_result!$B$3:$N$62,6,0)),"") -> 9.4819535e+08 | V94: 1.3 | W94: =IFERROR((S94*30%)/V94,0) -> 2.4312701e+08 | X94: =IFERROR(N94/W94,0) -> 0 | AA94: =IF(OR(U94="",Y94="",Z94=""),"",IF(AND(U94>Y94,-U94<Z94),"Ok","Not Ok"))
A95: =TB_audited!A78 -> Other revenues besides interest income | D95: =TB_audited!B78 -> 42201 | E95: =TB_audited!C78 -> 810/0040 | F95: =TB_audited!D78 -> UNREALISED GAIN / (LOSS) ON FOREIGN EXCHANGE | G95: =IF($D$8="Interim",TB_audited!G78,TB_audited!E78) -> -61347101 | H95: =IFERROR(VLOOKUP($A95,RA_result!$B$3:$N$62,11,0),"") | I95: =IFERROR(VLOOKUP($A95,RA_result!$B$3:$N$62,12,0),"") -> Ya | J95: =IFERROR(VLOOKUP($A95,RA_result!$B$3:$N$62,13,0),"") -> YE | M95: -61347101 | N95: =G95-M95 -> 0 | O95: =IFERROR(VLOOKUP($A95,RA_result!$B$3:$N$62,7,0),"") -> M | P95: =IFERROR(VLOOKUP($A95,RA_result!$B$3:$N$62,9,0),"") -> L | Q95: =IFERROR(VLOOKUP($A95,RA_result!$B$3:$N$62,10,0),"") | R95: N | S95: =IFERROR(VLOOKUP($A95,RA_result!$B$3:$N$62,4,0),"") -> 1.0535504e+09 | U95: =IFERROR(IF(VLOOKUP($A95,RA_result!$B$3:$N$62,6,0)="",S95*T95,VLOOKUP($A95,RA_result!$B$3:$N$62,6,0)),"") | W95: =IFERROR((S95*30%)/V95,0) -> 0 | X95: =IFERROR(N95/W95,0) -> 0 | AA95: =IF(OR(U95="",Y95="",Z95=""),"",IF(AND(U95>Y95,-U95<Z95),"Ok","Not Ok"))
A96: =TB_audited!A79 -> Other revenues besides interest income | D96: =TB_audited!B79 -> 42202 | E96: =TB_audited!C79 -> 820/0000 | F96: =TB_audited!D79 -> SUNDRY INCOME | G96: =IF($D$8="Interim",TB_audited!G79,TB_audited!E79) -> 10089.16 | H96: =IFERROR(VLOOKUP($A96,RA_result!$B$3:$N$62,11,0),"") | I96: =IFERROR(VLOOKUP($A96,RA_result!$B$3:$N$62,12,0),"") -> Ya | J96: =IFERROR(VLOOKUP($A96,RA_result!$B$3:$N$62,13,0),"") -> YE | M96: 10089.16 | N96: =G96-M96 -> 0 | O96: =IFERROR(VLOOKUP($A96,RA_result!$B$3:$N$62,7,0),"") -> M | P96: =IFERROR(VLOOKUP($A96,RA_result!$B$3:$N$62,9,0),"") -> L | Q96: =IFERROR(VLOOKUP($A96,RA_result!$B$3:$N$62,10,0),"") | R96: N | S96: =IFERROR(VLOOKUP($A96,RA_result!$B$3:$N$62,4,0),"") -> 1.0535504e+09 | U96: =IFERROR(IF(VLOOKUP($A96,RA_result!$B$3:$N$62,6,0)="",S96*T96,VLOOKUP($A96,RA_result!$B$3:$N$62,6,0)),"") | W96: =IFERROR((S96*30%)/V96,0) -> 0 | X96: =IFERROR(N96/W96,0) -> 0 | AA96: =IF(OR(U96="",Y96="",Z96=""),"",IF(AND(U96>Y96,-U96<Z96),"Ok","Not Ok"))
A97: =TB_audited!A80 -> Interest income | D97: =TB_audited!B80 -> 42101 | E97: =TB_audited!C80 -> 841/0000 | F97: =TB_audited!D80 -> INTEREST INCOME | G97: =IF($D$8="Interim",TB_audited!G80,TB_audited!E80) -> 5.4948148e+08 | H97: =IFERROR(VLOOKUP($A97,RA_result!$B$3:$N$62,11,0),"") | I97: =IFERROR(VLOOKUP($A97,RA_result!$B$3:$N$62,12,0),"") -> Ya | J97: =IFERROR(VLOOKUP($A97,RA_result!$B$3:$N$62,13,0),"") -> YE | K97: Tidak | L97: Ya | M97: 5.4948148e+08 | N97: =G97-M97 -> 0 | O97: =IFERROR(VLOOKUP($A97,RA_result!$B$3:$N$62,7,0),"") -> M | P97: =IFERROR(VLOOKUP($A97,RA_result!$B$3:$N$62,9,0),"") -> L | Q97: =IFERROR(VLOOKUP($A97,RA_result!$B$3:$N$62,10,0),"") | R97: N | S97: =IFERROR(VLOOKUP($A97,RA_result!$B$3:$N$62,4,0),"") -> 1.0535504e+09 | T97: 0.9 | U97: =IFERROR(IF(VLOOKUP($A97,RA_result!$B$3:$N$62,6,0)="",S97*T97,VLOOKUP($A97,RA_result!$B$3:$N$62,6,0)),"") -> 2.9499411e+08 | V97: 1.3 | W97: =IFERROR((S97*30%)/V97,0) -> 2.4312701e+08 | X97: =IFERROR(N97/W97,0) -> 0 | AA97: =IF(OR(U97="",Y97="",Z97=""),"",IF(AND(U97>Y97,-U97<Z97),"Ok","Not Ok"))
A98: =TB_audited!A81 -> Other revenues besides interest income | D98: =TB_audited!B81 -> 42203 | E98: =TB_audited!C81 -> 842/0000 | F98: =TB_audited!D81 -> TAX ON INTEREST INCOME | G98: =IF($D$8="Interim",TB_audited!G81,TB_audited!E81) -> -1.098963e+08 | H98: =IFERROR(VLOOKUP($A98,RA_result!$B$3:$N$62,11,0),"") | I98: =IFERROR(VLOOKUP($A98,RA_result!$B$3:$N$62,12,0),"") -> Ya | J98: =IFERROR(VLOOKUP($A98,RA_result!$B$3:$N$62,13,0),"") -> YE | M98: -1.098963e+08 | N98: =G98-M98 -> 0 | O98: =IFERROR(VLOOKUP($A98,RA_result!$B$3:$N$62,7,0),"") -> M | P98: =IFERROR(VLOOKUP($A98,RA_result!$B$3:$N$62,9,0),"") -> L | Q98: =IFERROR(VLOOKUP($A98,RA_result!$B$3:$N$62,10,0),"") | R98: N | S98: =IFERROR(VLOOKUP($A98,RA_result!$B$3:$N$62,4,0),"") -> 1.0535504e+09 | U98: =IFERROR(IF(VLOOKUP($A98,RA_result!$B$3:$N$62,6,0)="",S98*T98,VLOOKUP($A98,RA_result!$B$3:$N$62,6,0)),"") | W98: =IFERROR((S98*30%)/V98,0) -> 0 | X98: =IFERROR(N98/W98,0) -> 0 | AA98: =IF(OR(U98="",Y98="",Z98=""),"",IF(AND(U98>Y98,-U98<Z98),"Ok","Not Ok"))
A99: =TB_audited!A82 -> Other revenues besides interest income | D99: =TB_audited!B82 -> 42204 | E99: =TB_audited!C82 -> 850/0010 | F99: =TB_audited!D82 -> SALES-SCRAP WASTE ITEMS | G99: =IF($D$8="Interim",TB_audited!G82,TB_audited!E82) -> 0 | H99: =IFERROR(VLOOKUP($A99,RA_result!$B$3:$N$62,11,0),"") | I99: =IFERROR(VLOOKUP($A99,RA_result!$B$3:$N$62,12,0),"") -> Ya | J99: =IFERROR(VLOOKUP($A99,RA_result!$B$3:$N$62,13,0),"") -> YE | M99: 0 | N99: =G99-M99 -> 0 | O99: =IFERROR(VLOOKUP($A99,RA_result!$B$3:$N$62,7,0),"") -> M | P99: =IFERROR(VLOOKUP($A99,RA_result!$B$3:$N$62,9,0),"") -> L | Q99: =IFERROR(VLOOKUP($A99,RA_result!$B$3:$N$62,10,0),"") | R99: N | S99: =IFERROR(VLOOKUP($A99,RA_result!$B$3:$N$62,4,0),"") -> 1.0535504e+09 | U99: =IFERROR(IF(VLOOKUP($A99,RA_result!$B$3:$N$62,6,0)="",S99*T99,VLOOKUP($A99,RA_result!$B$3:$N$62,6,0)),"") | W99: =IFERROR((S99*30%)/V99,0) -> 0 | X99: =IFERROR(N99/W99,0) -> 0 | AA99: =IF(OR(U99="",Y99="",Z99=""),"",IF(AND(U99>Y99,-U99<Z99),"Ok","Not Ok"))
A100: =TB_audited!A83 -> Human resources expense | D100: =TB_audited!B83 -> 52101 | E100: =TB_audited!C83 -> 860/0000 | F100: =TB_audited!D83 -> EMPLOYEE BENEFIT | G100: =IF($D$8="Interim",TB_audited!G83,TB_audited!E83) -> 0 | H100: =IFERROR(VLOOKUP($A100,RA_result!$B$3:$N$62,11,0),"") | I100: =IFERROR(VLOOKUP($A100,RA_result!$B$3:$N$62,12,0),"") -> Ya | J100: =IFERROR(VLOOKUP($A100,RA_result!$B$3:$N$62,13,0),"") -> YE | M100: 0 | N100: =G100-M100 -> 0 | O100: =IFERROR(VLOOKUP($A100,RA_result!$B$3:$N$62,7,0),"") -> M | P100: =IFERROR(VLOOKUP($A100,RA_result!$B$3:$N$62,9,0),"") -> L | Q100: =IFERROR(VLOOKUP($A100,RA_result!$B$3:$N$62,10,0),"") | R100: N | S100: =IFERROR(VLOOKUP($A100,RA_result!$B$3:$N$62,4,0),"") -> 1.0535504e+09 | T100: 0.9 | U100: =IFERROR(IF(VLOOKUP($A100,RA_result!$B$3:$N$62,6,0)="",S100*T100,VLOOKUP($A100,RA_result!$B$3:$N$62,6,0)),"") -> 9.4819535e+08 | V100: 1.3 | W100: =IFERROR((S100*30%)/V100,0) -> 2.4312701e+08 | X100: =IFERROR(N100/W100,0) -> 0 | AA100: =IF(OR(U100="",Y100="",Z100=""),"",IF(AND(U100>Y100,-U100<Z100),"Ok","Not Ok"))
A101: =TB_audited!A84 -> General and administrative expense | D101: =TB_audited!B84 -> 52201 | E101: =TB_audited!C84 -> 910/0010 | F101: =TB_audited!D84 -> ACCOUNTING FEE | G101: =IF($D$8="Interim",TB_audited!G84,TB_audited!E84) -> 150000000 | H101: =IFERROR(VLOOKUP($A101,RA_result!$B$3:$N$62,11,0),"") | I101: =IFERROR(VLOOKUP($A101,RA_result!$B$3:$N$62,12,0),"") | J101: =IFERROR(VLOOKUP($A101,RA_result!$B$3:$N$62,13,0),"") | K101: Tidak | L101: Ya | M101: 90000000 | N101: =G101-M101 -> 60000000 | O101: =IFERROR(VLOOKUP($A101,RA_result!$B$3:$N$62,7,0),"") -> TM | P101: =IFERROR(VLOOKUP($A101,RA_result!$B$3:$N$62,9,0),"") -> L | Q101: =IFERROR(VLOOKUP($A101,RA_result!$B$3:$N$62,10,0),"") | R101: N | S101: =IFERROR(VLOOKUP($A101,RA_result!$B$3:$N$62,4,0),"") -> 1.0535504e+09 | T101: 0.9 | U101: =IFERROR(IF(VLOOKUP($A101,RA_result!$B$3:$N$62,6,0)="",S101*T101,VLOOKUP($A101,RA_result!$B$3:$N$62,6,0)),"") -> 9.4819535e+08 | V101: 2.3 | W101: =IFERROR((S101*30%)/V101,0) -> 1.3741962e+08 | X101: =IFERROR(N101/W101,0) -> 0.43661889 | AA101: =IF(OR(U101="",Y101="",Z101=""),"",IF(AND(U101>Y101,-U101<Z101),"Ok","Not Ok"))
A102: =TB_audited!A85 -> General and administrative expense | D102: =TB_audited!B85 -> 52202 | E102: =TB_audited!C85 -> 910/0020 | F102: =TB_audited!D85 -> AUDIT FEE | G102: =IF($D$8="Interim",TB_audited!G85,TB_audited!E85) -> 50500000 | H102: =IFERROR(VLOOKUP($A102,RA_result!$B$3:$N$62,11,0),"") | I102: =IFERROR(VLOOKUP($A102,RA_result!$B$3:$N$62,12,0),"") | J102: =IFERROR(VLOOKUP($A102,RA_result!$B$3:$N$62,13,0),"") | K102: Ya | L102: Tidak | M102: 50500000 | N102: =G102-M102 -> 0 | O102: =IFERROR(VLOOKUP($A102,RA_result!$B$3:$N$62,7,0),"") -> TM | P102: =IFERROR(VLOOKUP($A102,RA_result!$B$3:$N$62,9,0),"") -> L | Q102: =IFERROR(VLOOKUP($A102,RA_result!$B$3:$N$62,10,0),"") | R102: N | S102: =IFERROR(VLOOKUP($A102,RA_result!$B$3:$N$62,4,0),"") -> 1.0535504e+09 | T102: 0.9 | U102: =IFERROR(IF(VLOOKUP($A102,RA_result!$B$3:$N$62,6,0)="",S102*T102,VLOOKUP($A102,RA_result!$B$3:$N$62,6,0)),"") -> 9.4819535e+08 | V102: 2.3 | W102: =IFERROR((S102*30%)/V102,0) -> 1.3741962e+08 | X102: =IFERROR(N102/W102,0) -> 0 | AA102: =IF(OR(U102="",Y102="",Z102=""),"",IF(AND(U102>Y102,-U102<Z102),"Ok","Not Ok"))
A103: =TB_audited!A86 -> General and administrative expense | D103: =TB_audited!B86 -> 52203 | E103: =TB_audited!C86 -> 910/0030 | F103: =TB_audited!D86 -> BANK CHARGES | G103: =IF($D$8="Interim",TB_audited!G86,TB_audited!E86) -> 23508742 | H103: =IFERROR(VLOOKUP($A103,RA_result!$B$3:$N$62,11,0),"") | I103: =IFERROR(VLOOKUP($A103,RA_result!$B$3:$N$62,12,0),"") | J103: =IFERROR(VLOOKUP($A103,RA_result!$B$3:$N$62,13,0),"") | K103: Ya | L103: Tidak | M103: 23508742 | N103: =G103-M103 -> 0 | O103: =IFERROR(VLOOKUP($A103,RA_result!$B$3:$N$62,7,0),"") -> TM | P103: =IFERROR(VLOOKUP($A103,RA_result!$B$3:$N$62,9,0),"") -> L | Q103: =IFERROR(VLOOKUP($A103,RA_result!$B$3:$N$62,10,0),"") | R103: N | S103: =IFERROR(VLOOKUP($A103,RA_result!$B$3:$N$62,4,0),"") -> 1.0535504e+09 | T103: 0.9 | U103: =IFERROR(IF(VLOOKUP($A103,RA_result!$B$3:$N$62,6,0)="",S103*T103,VLOOKUP($A103,RA_result!$B$3:$N$62,6,0)),"") -> 9.4819535e+08 | V103: 2.3 | W103: =IFERROR((S103*30%)/V103,0) -> 1.3741962e+08 | X103: =IFERROR(N103/W103,0) -> 0 | AA103: =IF(OR(U103="",Y103="",Z103=""),"",IF(AND(U103>Y103,-U103<Z103),"Ok","Not Ok"))
A104: =TB_audited!A87 -> Human resources expense | D104: =TB_audited!B87 -> 52102 | E104: =TB_audited!C87 -> 910/0060 | F104: =TB_audited!D87 -> JAMSOSTEK CONTRIBUTION | G104: =IF($D$8="Interim",TB_audited!G87,TB_audited!E87) -> 329077573 | H104: =IFERROR(VLOOKUP($A104,RA_result!$B$3:$N$62,11,0),"") | I104: =IFERROR(VLOOKUP($A104,RA_result!$B$3:$N$62,12,0),"") -> Ya | J104: =IFERROR(VLOOKUP($A104,RA_result!$B$3:$N$62,13,0),"") -> YE | K104: Ya | L104: Tidak | M104: 329077573 | N104: =G104-M104 -> 0 | O104: =IFERROR(VLOOKUP($A104,RA_result!$B$3:$N$62,7,0),"") -> M | P104: =IFERROR(VLOOKUP($A104,RA_result!$B$3:$N$62,9,0),"") -> L | Q104: =IFERROR(VLOOKUP($A104,RA_result!$B$3:$N$62,10,0),"") | R104: N | S104: =IFERROR(VLOOKUP($A104,RA_result!$B$3:$N$62,4,0),"") -> 1.0535504e+09 | T104: 0.9 | U104: =IFERROR(IF(VLOOKUP($A104,RA_result!$B$3:$N$62,6,0)="",S104*T104,VLOOKUP($A104,RA_result!$B$3:$N$62,6,0)),"") -> 9.4819535e+08 | V104: 2.3 | W104: =IFERROR((S104*30%)/V104,0) -> 1.3741962e+08 | X104: =IFERROR(N104/W104,0) -> 0 | AA104: =IF(OR(U104="",Y104="",Z104=""),"",IF(AND(U104>Y104,-U104<Z104),"Ok","Not Ok"))
A105: =TB_audited!A88 -> General and administrative expense | D105: =TB_audited!B88 -> 52204 | E105: =TB_audited!C88 -> 910/0070 | F105: =TB_audited!D88 -> FOOD AND DRINKS | G105: =IF($D$8="Interim",TB_audited!G88,TB_audited!E88) -> 6656691.9 | H105: =IFERROR(VLOOKUP($A105,RA_result!$B$3:$N$62,11,0),"") | I105: =IFERROR(VLOOKUP($A105,RA_result!$B$3:$N$62,12,0),"") | J105: =IFERROR(VLOOKUP($A105,RA_result!$B$3:$N$62,13,0),"") | M105: 6656691.9 | N105: =G105-M105 -> 0 | O105: =IFERROR(VLOOKUP($A105,RA_result!$B$3:$N$62,7,0),"") -> TM | P105: =IFERROR(VLOOKUP($A105,RA_result!$B$3:$N$62,9,0),"") -> L | Q105: =IFERROR(VLOOKUP($A105,RA_result!$B$3:$N$62,10,0),"") | R105: N | S105: =IFERROR(VLOOKUP($A105,RA_result!$B$3:$N$62,4,0),"") -> 1.0535504e+09 | T105: 0.9 | U105: =IFERROR(IF(VLOOKUP($A105,RA_result!$B$3:$N$62,6,0)="",S105*T105,VLOOKUP($A105,RA_result!$B$3:$N$62,6,0)),"") -> 9.4819535e+08 | V105: 2.3 | W105: =IFERROR((S105*30%)/V105,0) -> 1.3741962e+08 | X105: =IFERROR(N105/W105,0) -> 0 | AA105: =IF(OR(U105="",Y105="",Z105=""),"",IF(AND(U105>Y105,-U105<Z105),"Ok","Not Ok"))
...

Sheet RA_result
A1: RA.120 | C1: 0 | D1: RA.220 | I1: RA.230 | L1: Periksa
A2: Kode | B2: Header | C2: 0 | D2: OM | E2: PM | F2: SM-OM | G2: SM-PM | I2: ASERSI | J2: ROMM | K2: SA | L2: AP | M2: TOD | N2: Saat
A3: Kode | B3: Header | C3: 45657 | D3: OM | E3: PM | F3: SM-OM | G3: SM-PM | H3: PM | I3: ASERSI | J3: ROMM | K3: SA | L3: AP | M3: TOD | N3: Saat
A4: 111 | B4: Cash and cash equivalent | C4: 3.4320162e+10 | D4: 1.505072e+09 | E4: 1.0535504e+09 | H4: M | I4: E V | J4: L | M4: Ya | N4: YE
A5: 112 | B5: Trade receivable | C5: 16281458401 | D5: 1.505072e+09 | E5: 1.0535504e+09 | H5: M | I5: E V | J5: M | M5: Ya | N5: YE
A6: 116 | B6: Inventory | C6: 1.4229503e+10 | D6: 1.505072e+09 | E6: 1.0535504e+09 | H6: M | I6: E V | J6: L | M6: Ya | N6: YE
A7: 117 | B7: Prepayment | C7: 2133021044 | D7: 1.505072e+09 | E7: 1.0535504e+09 | H7: M | I7: E V | J7: M | L7: Ya | M7: Ya | N7: YE
A8: 118 | B8: Prepaid tax | C8: 499052369 | D8: 1.505072e+09 | E8: 1.0535504e+09 | F8: 4.2142016e+08 | G8: 2.9499411e+08 | H8: M | I8: E V | J8: L | M8: Ya | N8: YE
A9: 119 | B9: Other current asset | C9: 35200000 | D9: 1.505072e+09 | E9: 1.0535504e+09 | H9: TM | I9: E V | J9: L
A10: 125 | B10: Fixed asset | C10: 7776927237 | D10: 1.505072e+09 | E10: 1.0535504e+09 | H10: M | I10: E V | J10: L | L10: Ya | M10: Ya | N10: YE
A11: 127 | B11: Intangible asset | C11: 0 | D11: 1.505072e+09 | E11: 1.0535504e+09 | H11: TM | I11: E V | J11: L
A12: 211 | B12: Trade payable | C12: 1.2695742e+10 | D12: 1.505072e+09 | E12: 1.0535504e+09 | H12: M | I12: C V | J12: L | M12: Ya | N12: YE
A13: 212 | B13: Accruals and other payable | C13: 15873194 | D13: 1.505072e+09 | E13: 1.0535504e+09 | H13: TM | I13: C V | J13: L
A14: 216 | B14: Short-term employee benefit liability | C14: 1247188889 | D14: 1.505072e+09 | E14: 1.0535504e+09 | H14: M | I14: C V | J14: L | M14: Ya | N14: YE
A15: 217 | B15: Taxes payable | C15: 501182221 | D15: 1.505072e+09 | E15: 1.0535504e+09 | F15: 4.2142016e+08 | G15: 2.9499411e+08 | H15: M | I15: C V | J15: L | M15: Ya | N15: YE
A16: 229 | B16: Other long-term liability | C16: 2775984576 | D16: 1.505072e+09 | E16: 1.0535504e+09 | H16: M | I16: C V | J16: L | M16: Ya | N16: YE
A17: 311 | B17: Share capital | C17: 10500000000 | D17: 1.505072e+09 | E17: 1.0535504e+09 | H17: M | I17: E V | J17: L | M17: Ya | N17: YE
A18: 332 | B18: Retained earnings – unappropriated | C18: 31480858157 | D18: 1.505072e+09 | E18: 1.0535504e+09 | H18: M | I18: E V | J18: L | M18: Ya | N18: YE
A19: 411 | B19: Revenue | C19: 8.3417567e+10 | D19: 1.505072e+09 | E19: 1.0535504e+09 | H19: M | I19: E A&C | J19: H | M19: Ya | N19: YE
A20: 421 | B20: Interest income | C20: 5.4948148e+08 | D20: 1.505072e+09 | E20: 1.0535504e+09 | F20: 4.2142016e+08 | G20: 2.9499411e+08 | H20: M | I20: E A&C | J20: L | M20: Ya | N20: YE
A21: 422 | B21: Other revenues besides interest income | C21: -1.7123331e+08 | D21: 1.505072e+09 | E21: 1.0535504e+09 | H21: M | I21: C A&C | J21: L | M21: Ya | N21: YE
A22: 511 | B22: Cost of revenue | C22: 5.1089641e+10 | D22: 1.505072e+09 | E22: 1.0535504e+09 | H22: M | I22: C A&C | J22: L | M22: Ya | N22: YE
A23: 521 | B23: Human resources expense | C23: 3418854851 | D23: 1.505072e+09 | E23: 1.0535504e+09 | H23: M | I23: C A&C | J23: L | M23: Ya | N23: YE
A24: 522 | B24: General and administrative expense | C24: 3.8755874e+09 | D24: 1.505072e+09 | E24: 1.0535504e+09 | H24: TM | I24: C A&C | J24: L
A25: 523 | B25: Depreciation and amortization expense | C25: 495378476 | D25: 1.505072e+09 | E25: 1.0535504e+09 | H25: M | I25: C A&C | J25: L | M25: Ya | N25: YE
A26: 532 | B26: Other expenses besides interest expense | C26: 3.4153249e+09 | D26: 1.505072e+09 | E26: 1.0535504e+09 | H26: M | I26: C A&C | J26: L | M26: Ya | N26: YE
A27: 541 | B27: Current tax expense | C27: 5442533360 | D27: 1.505072e+09 | E27: 1.0535504e+09 | H27: M | I27: C A&C | J27: L | M27: Ya | N27: YE
A63: X | B63: X | C63: X | D63: X | E63: X | F63: X | G63: X | H63: X | I63: X | J63: X | K63: X | L63: X | M63: X | N63: X

Sheet TB_audited
A1: Trial Balance | E1: Current | F1: Previous | G1: Interim
A2: header | B2: no_N | C2: no_O | D2: nama_akun | E2: 45657 | F2: 45291 | G2: 45657
A3: Trade receivable | B3: 11201 | C3: 100/0000 | D3: TRADE DEBTORS - IDR | E3: 18567911215 | F3: 22990014172 | G3: 18567911215
A4: Trade receivable | B4: 11202 | C4: 100/0001 | D4: Provision of Allowance Bad Debts | E4: -2286452814 | F4: -1143226407 | G4: -2286452814
A5: Other current asset | B5: 11901 | C5: 105/0010 | D5: YKL ENGINEERING SDN. BHD. (PJS) | E5: 0 | F5: 16000000 | G5: 0
A6: Other current asset | B6: 11902 | C6: 105/0060 | D6: PT. KMT ENGINEERING NUSANTARA (PJS) | E6: 0 | F6: 0 | G6: 0
A7: Cash and cash equivalent | B7: 11101 | C7: 110/0000 | D7: CASH IN HAND | E7: 23836004 | F7: 15160437 | G7: 23836004
A8: Cash and cash equivalent | B8: 11102 | C8: 120/0030 | D8: CASH AT BANK-BCA (2ND) A/C : 764BCA (2ND) A/C : 7640669998 IDR | E8: 21825626 | F8: 993712492 | G8: 21825626
A9: Cash and cash equivalent | B9: 11103 | C9: 120/0040 | D9: CASH AT BANK-BCA (EMG) A/C : 764BCA (EMG) A/C : 7640669599 IDR | E9: 2.487905e+08 | F9: 309372414 | G9: 2.487905e+08
A10: Cash and cash equivalent | B10: 11104 | C10: 120/0050 | D10: CASH AT BANK-MANDIRI A/C : 118003MANDIRI A/C : 1180033355677 IDR | E10: 3.3120579e+10 | F10: 26887905412 | G10: 3.3120579e+10
A11: Cash and cash equivalent | B11: 11105 | C11: 120/0100 | D11: CASH AT BANK-MANDIRI A/C : 1180007MANDIRI A/C : 1180007832388 USD2 | E11: 0 | F11: 0 | G11: 0
A12: Cash and cash equivalent | B12: 11106 | C12: 120/0140 | D12: CASH AT BANK-BNI A/C:855771775 | E12: 905130602 | F12: 897718588 | G12: 905130602
A13: Inventory | B13: 11601 | C13: 126/1000 | D13: INVENTORY-MACHINE | E13: 333000000 | F13: 333000000 | G13: 333000000
A14: Inventory | B14: 11602 | C14: 126/2000 | D14: INVENTORY-SPAREPARTS | E14: 1.3896503e+10 | F14: 9896961465 | G14: 1.3896503e+10
... A128: General and administrative expense | B128: 52230 | C128: 980/0020 | D128: Taxation | E128: 558931077 | F128: 0 | G128: 558931077
A1003: X | B1003: X | C1003: X | D1003: X | E1003: X | F1003: X | G1003: X
